{
    "BriefingText": "BRIEFING\r\n\r\nThe Reaction Control System consists of the systems required to maneuver in space. This includes both attitude and translational control, and what systems that makes this possible. The SM has 16 thrusters for movement in all axes, while the CM has 12 for attitude control in all axes.",
    "CommandModulePilot": "Patrick",
    "Description": "The Reaction Control System consists of the systems required to maneuver in space. This includes both attitude and translational control, and what systems that makes this possible. The SM has 16 thrusters for movement in all axes, while the CM has 12 for attitude control in all axes.",
    "FlightPlanPrefabId": 0,
    "Id": 103,
    "Inclination": 72.5,
    "InitialTimeToRetrograde": "10:00:00",
    "LoadState": "state_apolloFreeFlightCSMOrbit",
    "LunarModulePilot": "Paul",
    "MinutesBeforeLaunch": 25.0,
    "MissionActivities": [],
    "MissionCommands": [
        {
            "Action": 0,
            "Bool1": false,
            "ButtonId": 0,
            "Completed": false,
            "Delivered": false,
            "DisplayTime": 5.0,
            "Fault": 0,
            "From": 2,
            "FuseID": 0,
            "FusePosition": 0,
            "KnobID": 0,
            "Message": "Welcome to the RCS lesson! The Reaction Control System is a set of systems that control the jet thrusters used to maneuver the spacecraft in orbit.",
            "PinID": 0,
            "PinPosition": 0,
            "String1": null,
            "String2": null,
            "String3": null,
            "ThresholdLimit": 0.0,
            "Timestamp": 0.0,
            "Value1": 0.0,
            "Value2": 0.0,
            "Value3": 0.0
        },
        {
            "Action": 0,
            "Bool1": false,
            "ButtonId": 0,
            "Completed": false,
            "Delivered": false,
            "DisplayTime": 5.0,
            "Fault": 0,
            "From": 2,
            "FuseID": 0,
            "FusePosition": 0,
            "KnobID": 0,
            "Message": "The Service Module RCS system is primarly used throught the mission until CM/SM separation.",
            "PinID": 0,
            "PinPosition": 0,
            "String1": null,
            "String2": null,
            "String3": null,
            "ThresholdLimit": 0.0,
            "Timestamp": 0.0,
            "Value1": 0.0,
            "Value2": 0.0,
            "Value3": 0.0
        },
        {
            "Action": 0,
            "Bool1": false,
            "ButtonId": 0,
            "Completed": false,
            "Delivered": false,
            "DisplayTime": 5.0,
            "Fault": 0,
            "From": 2,
            "FuseID": 0,
            "FusePosition": 0,
            "KnobID": 0,
            "Message": "The SM RCS system consists of four identical packages/quads located on the SM. Each pack is distributed 90 degrees apart from each other.",
            "PinID": 0,
            "PinPosition": 0,
            "String1": null,
            "String2": null,
            "String3": null,
            "ThresholdLimit": 0.0,
            "Timestamp": 0.0,
            "Value1": 0.0,
            "Value2": 0.0,
            "Value3": 0.0
        },
        {
            "Action": 0,
            "Bool1": false,
            "ButtonId": 0,
            "Completed": false,
            "Delivered": false,
            "DisplayTime": 5.0,
            "Fault": 0,
            "From": 2,
            "FuseID": 0,
            "FusePosition": 0,
            "KnobID": 0,
            "Message": "Each package has four jets/thrusters that can be fired. Each pack is named A, B, C and D, and each thruster on a pack is named 1, 2, 3 and 4.",
            "PinID": 0,
            "PinPosition": 0,
            "String1": null,
            "String2": null,
            "String3": null,
            "ThresholdLimit": 0.0,
            "Timestamp": 0.0,
            "Value1": 0.0,
            "Value2": 0.0,
            "Value3": 0.0
        },
        {
            "Action": 0,
            "Bool1": false,
            "ButtonId": 0,
            "Completed": false,
            "Delivered": false,
            "DisplayTime": 5.0,
            "Fault": 0,
            "From": 2,
            "FuseID": 0,
            "FusePosition": 0,
            "KnobID": 0,
            "Message": "Using this convention, a jet can be referred to as for example D3, meaining jet three on quad D.",
            "PinID": 0,
            "PinPosition": 0,
            "String1": null,
            "String2": null,
            "String3": null,
            "ThresholdLimit": 0.0,
            "Timestamp": 0.0,
            "Value1": 0.0,
            "Value2": 0.0,
            "Value3": 0.0
        },
        {
            "Action": 0,
            "Bool1": false,
            "ButtonId": 0,
            "Completed": false,
            "Delivered": false,
            "DisplayTime": 5.0,
            "Fault": 0,
            "From": 2,
            "FuseID": 0,
            "FusePosition": 0,
            "KnobID": 0,
            "Message": "In addition, each quad has its own propulsion system. Helium is used to pressurize the quad so fuel/oxidizer gets mixed and ignite.",
            "PinID": 0,
            "PinPosition": 0,
            "String1": null,
            "String2": null,
            "String3": null,
            "ThresholdLimit": 0.0,
            "Timestamp": 0.0,
            "Value1": 0.0,
            "Value2": 0.0,
            "Value3": 0.0
        },
        {
            "Action": 0,
            "Bool1": false,
            "ButtonId": 0,
            "Completed": false,
            "Delivered": false,
            "DisplayTime": 5.0,
            "Fault": 0,
            "From": 2,
            "FuseID": 0,
            "FusePosition": 0,
            "KnobID": 0,
            "Message": "Two helium tanks exist in each quad, as well as two propulsion systems. To use the jets on a quad, the helium valves needs to be open, as well as the propulsion system.",
            "PinID": 0,
            "PinPosition": 0,
            "String1": null,
            "String2": null,
            "String3": null,
            "ThresholdLimit": 0.0,
            "Timestamp": 0.0,
            "Value1": 0.0,
            "Value2": 0.0,
            "Value3": 0.0
        },
        {
            "Action": 0,
            "Bool1": false,
            "ButtonId": 0,
            "Completed": false,
            "Delivered": false,
            "DisplayTime": 5.0,
            "Fault": 0,
            "From": 2,
            "FuseID": 0,
            "FusePosition": 0,
            "KnobID": 0,
            "Message": "Eight switches on MDC-2 control the Helium valves in each quad. The helium surrounds the bladder with propellant.",
            "PinID": 0,
            "PinPosition": 0,
            "String1": null,
            "String2": null,
            "String3": null,
            "ThresholdLimit": 0.0,
            "Timestamp": 0.0,
            "Value1": 0.0,
            "Value2": 0.0,
            "Value3": 0.0
        },
        {
            "Action": 0,
            "Bool1": false,
            "ButtonId": 0,
            "Completed": false,
            "Delivered": false,
            "DisplayTime": 5.0,
            "Fault": 0,
            "From": 2,
            "FuseID": 0,
            "FusePosition": 0,
            "KnobID": 0,
            "Message": "There is one switch per quad, per helium system.",
            "PinID": 0,
            "PinPosition": 0,
            "String1": null,
            "String2": null,
            "String3": null,
            "ThresholdLimit": 0.0,
            "Timestamp": 0.0,
            "Value1": 0.0,
            "Value2": 0.0,
            "Value3": 0.0
        },
        {
            "Action": 200,
            "Bool1": false,
            "ButtonId": 0,
            "Completed": false,
            "Delivered": false,
            "DisplayTime": 5.0,
            "Fault": 0,
            "From": 2,
            "FuseID": 0,
            "FusePosition": 0,
            "KnobID": 0,
            "Message": "Set the SM RCS HELIUM 1 quad D switch to the up position. This will open the helium 1 valve in quad D.",
            "PinID": 86,
            "PinPosition": 4,
            "String1": null,
            "String2": null,
            "String3": null,
            "ThresholdLimit": 0.0,
            "Timestamp": 0.0,
            "Value1": 0.0,
            "Value2": 0.0,
            "Value3": 0.0
        },
        {
            "Action": 0,
            "Bool1": false,
            "ButtonId": 0,
            "Completed": false,
            "Delivered": false,
            "DisplayTime": 5.0,
            "Fault": 0,
            "From": 2,
            "FuseID": 0,
            "FusePosition": 0,
            "KnobID": 0,
            "Message": "A talkback indicator indicates gray if the valve is open, and barberpoled if closed.",
            "PinID": 0,
            "PinPosition": 0,
            "String1": null,
            "String2": null,
            "String3": null,
            "ThresholdLimit": 0.0,
            "Timestamp": 0.0,
            "Value1": 0.0,
            "Value2": 0.0,
            "Value3": 0.0
        },
        {
            "Action": 200,
            "Bool1": false,
            "ButtonId": 0,
            "Completed": false,
            "Delivered": false,
            "DisplayTime": 5.0,
            "Fault": 0,
            "From": 2,
            "FuseID": 0,
            "FusePosition": 0,
            "KnobID": 0,
            "Message": "Set the SM RCS HELIUM 1 quad D switch to the down position. The valve is closed and barberpole is visible.",
            "PinID": 86,
            "PinPosition": 5,
            "String1": null,
            "String2": null,
            "String3": null,
            "ThresholdLimit": 0.0,
            "Timestamp": 0.0,
            "Value1": 0.0,
            "Value2": 0.0,
            "Value3": 0.0
        },
        {
            "Action": 0,
            "Bool1": false,
            "ButtonId": 0,
            "Completed": false,
            "Delivered": false,
            "DisplayTime": 5.0,
            "Fault": 0,
            "From": 2,
            "FuseID": 0,
            "FusePosition": 0,
            "KnobID": 0,
            "Message": "The SM RCS Propellant system works the same way, but using the 8 switches just below the helium controls.",
            "PinID": 0,
            "PinPosition": 0,
            "String1": null,
            "String2": null,
            "String3": null,
            "ThresholdLimit": 0.0,
            "Timestamp": 0.0,
            "Value1": 0.0,
            "Value2": 0.0,
            "Value3": 0.0
        },
        {
            "Action": 201,
            "Bool1": false,
            "ButtonId": 0,
            "Completed": false,
            "Delivered": false,
            "DisplayTime": 5.0,
            "Fault": 0,
            "From": 2,
            "FuseID": 0,
            "FusePosition": 0,
            "KnobID": 6,
            "Message": "Each quad can be monitored using the RCS INDICATOR rotator knob on MDC-2, set it to SM RCS QUAD D.",
            "PinID": 0,
            "PinPosition": 0,
            "String1": null,
            "String2": null,
            "String3": null,
            "ThresholdLimit": 0.0,
            "Timestamp": 0.0,
            "Value1": 5.0,
            "Value2": 0.0,
            "Value3": 0.0
        },
        {
            "Action": 0,
            "Bool1": false,
            "ButtonId": 0,
            "Completed": false,
            "Delivered": false,
            "DisplayTime": 5.0,
            "Fault": 0,
            "From": 2,
            "FuseID": 0,
            "FusePosition": 0,
            "KnobID": 0,
            "Message": "The SM RCS gauges are used to monitor the quads, including the CM systems.",
            "PinID": 0,
            "PinPosition": 0,
            "String1": null,
            "String2": null,
            "String3": null,
            "ThresholdLimit": 0.0,
            "Timestamp": 0.0,
            "Value1": 0.0,
            "Value2": 0.0,
            "Value3": 0.0
        },
        {
            "Action": 200,
            "Bool1": false,
            "ButtonId": 0,
            "Completed": false,
            "Delivered": false,
            "DisplayTime": 5.0,
            "Fault": 0,
            "From": 2,
            "FuseID": 0,
            "FusePosition": 0,
            "KnobID": 0,
            "Message": "The SM RCS IND switch selects if the last gauge above will show the Helium Tank Temperature or the Propellant Quantity. Set it to Propellant Qunatity (down).",
            "PinID": 101,
            "PinPosition": 5,
            "String1": null,
            "String2": null,
            "String3": null,
            "ThresholdLimit": 0.0,
            "Timestamp": 0.0,
            "Value1": 0.0,
            "Value2": 0.0,
            "Value3": 0.0
        },
        {
            "Action": 0,
            "Bool1": false,
            "ButtonId": 0,
            "Completed": false,
            "Delivered": false,
            "DisplayTime": 5.0,
            "Fault": 0,
            "From": 2,
            "FuseID": 0,
            "FusePosition": 0,
            "KnobID": 0,
            "Message": "Heaters are used to increase the temperature in the quad if they have been idle for a long time, or has a low temperature.",
            "PinID": 0,
            "PinPosition": 0,
            "String1": null,
            "String2": null,
            "String3": null,
            "ThresholdLimit": 0.0,
            "Timestamp": 0.0,
            "Value1": 0.0,
            "Value2": 0.0,
            "Value3": 0.0
        },
        {
            "Action": 0,
            "Bool1": false,
            "ButtonId": 0,
            "Completed": false,
            "Delivered": false,
            "DisplayTime": 5.0,
            "Fault": 0,
            "From": 2,
            "FuseID": 0,
            "FusePosition": 0,
            "KnobID": 0,
            "Message": "The Command Module RCS system has 12 thrusters and provides attitude control of the spacecraft.",
            "PinID": 0,
            "PinPosition": 0,
            "String1": null,
            "String2": null,
            "String3": null,
            "ThresholdLimit": 0.0,
            "Timestamp": 0.0,
            "Value1": 0.0,
            "Value2": 0.0,
            "Value3": 0.0
        },
        {
            "Action": 0,
            "Bool1": false,
            "ButtonId": 0,
            "Completed": false,
            "Delivered": false,
            "DisplayTime": 5.0,
            "Fault": 0,
            "From": 2,
            "FuseID": 0,
            "FusePosition": 0,
            "KnobID": 0,
            "Message": "Two redundant systems named 1 and 2 are used to control the 12 thrusters. As with the SM RCS system, helium is used to pressurize the systems.",
            "PinID": 0,
            "PinPosition": 0,
            "String1": null,
            "String2": null,
            "String3": null,
            "ThresholdLimit": 0.0,
            "Timestamp": 0.0,
            "Value1": 0.0,
            "Value2": 0.0,
            "Value3": 0.0
        },
        {
            "Action": 200,
            "Bool1": false,
            "ButtonId": 0,
            "Completed": false,
            "Delivered": false,
            "DisplayTime": 5.0,
            "Fault": 0,
            "From": 2,
            "FuseID": 0,
            "FusePosition": 0,
            "KnobID": 0,
            "Message": "Set the CM RCS PRESS switch to the up position to pressurize the CM RCS thrusters.",
            "PinID": 155,
            "PinPosition": 4,
            "String1": null,
            "String2": null,
            "String3": null,
            "ThresholdLimit": 0.0,
            "Timestamp": 0.0,
            "Value1": 0.0,
            "Value2": 0.0,
            "Value3": 0.0
        },
        {
            "Action": 0,
            "Bool1": false,
            "ButtonId": 0,
            "Completed": false,
            "Delivered": false,
            "DisplayTime": 5.0,
            "Fault": 0,
            "From": 2,
            "FuseID": 0,
            "FusePosition": 0,
            "KnobID": 0,
            "Message": "Then the CM RCS Propellant system needs to be pressurized. This is done with the two CM RCS PRPLNT switches. Set CM RCS PRPLNT 1 to UP.",
            "PinID": 99,
            "PinPosition": 4,
            "String1": null,
            "String2": null,
            "String3": null,
            "ThresholdLimit": 0.0,
            "Timestamp": 0.0,
            "Value1": 0.0,
            "Value2": 0.0,
            "Value3": 0.0
        },
        {
            "Action": 0,
            "Bool1": false,
            "ButtonId": 0,
            "Completed": false,
            "Delivered": false,
            "DisplayTime": 5.0,
            "Fault": 0,
            "From": 2,
            "FuseID": 0,
            "FusePosition": 0,
            "KnobID": 0,
            "Message": "Notice that the propellant system 1 is now pressurized by the talkback indicator.",
            "PinID": 0,
            "PinPosition": 0,
            "String1": null,
            "String2": null,
            "String3": null,
            "ThresholdLimit": 0.0,
            "Timestamp": 0.0,
            "Value1": 0.0,
            "Value2": 0.0,
            "Value3": 0.0
        },
        {
            "Action": 200,
            "Bool1": false,
            "ButtonId": 0,
            "Completed": false,
            "Delivered": false,
            "DisplayTime": 5.0,
            "Fault": 0,
            "From": 2,
            "FuseID": 0,
            "FusePosition": 0,
            "KnobID": 0,
            "Message": "The last thing needed is to enable the CM RCS LOGIC. This is automatically done during SM/CM separation if the CM RCS LOGIC (MDC-1) is enabled. If not, set the RCS TRNFR switch to use the CM RCS thrusters. Set it to UP.",
            "PinID": 154,
            "PinPosition": 4,
            "String1": null,
            "String2": null,
            "String3": null,
            "ThresholdLimit": 0.0,
            "Timestamp": 0.0,
            "Value1": 0.0,
            "Value2": 0.0,
            "Value3": 0.0
        },
        {
            "Action": 0,
            "Bool1": false,
            "ButtonId": 0,
            "Completed": false,
            "Delivered": false,
            "DisplayTime": 5.0,
            "Fault": 0,
            "From": 2,
            "FuseID": 0,
            "FusePosition": 0,
            "KnobID": 0,
            "Message": "Now the spacecraft is configured to use the CM RCS system instead of the SM RCS system. This is good in-case of emergencies, or essential after SM separation.",
            "PinID": 0,
            "PinPosition": 0,
            "String1": null,
            "String2": null,
            "String3": null,
            "ThresholdLimit": 0.0,
            "Timestamp": 0.0,
            "Value1": 0.0,
            "Value2": 0.0,
            "Value3": 0.0
        },
        {
            "Action": 0,
            "Bool1": false,
            "ButtonId": 0,
            "Completed": false,
            "Delivered": false,
            "DisplayTime": 5.0,
            "Fault": 0,
            "From": 2,
            "FuseID": 0,
            "FusePosition": 0,
            "KnobID": 0,
            "Message": "Each thruster has a direct and an automatic coil. The automatic coil is powered by either MNA or MNB and is configured by the 16 switches on Panel 8. Auto is using a system named the RJ/EC to control the thrusters.",
            "PinID": 0,
            "PinPosition": 0,
            "String1": null,
            "String2": null,
            "String3": null,
            "ThresholdLimit": 0.0,
            "Timestamp": 0.0,
            "Value1": 0.0,
            "Value2": 0.0,
            "Value3": 0.0
        },
        {
            "Action": 0,
            "Bool1": false,
            "ButtonId": 0,
            "Completed": false,
            "Delivered": false,
            "DisplayTime": 5.0,
            "Fault": 0,
            "From": 2,
            "FuseID": 0,
            "FusePosition": 0,
            "KnobID": 0,
            "Message": "The RJ/EC (Reaction Jet and Engine On/Off Control) is used by the SCS and CMC to trigger the right thrusters based on commands from the control sticks or the digital autopilot/CMC.",
            "PinID": 0,
            "PinPosition": 0,
            "String1": null,
            "String2": null,
            "String3": null,
            "ThresholdLimit": 0.0,
            "Timestamp": 0.0,
            "Value1": 0.0,
            "Value2": 0.0,
            "Value3": 0.0
        },
        {
            "Action": 0,
            "Bool1": false,
            "ButtonId": 0,
            "Completed": false,
            "Delivered": false,
            "DisplayTime": 5.0,
            "Fault": 0,
            "From": 2,
            "FuseID": 0,
            "FusePosition": 0,
            "KnobID": 0,
            "Message": "The direct coils are controlled directly from stick input if enabled, by-passing the electrical control systems.",
            "PinID": 0,
            "PinPosition": 0,
            "String1": null,
            "String2": null,
            "String3": null,
            "ThresholdLimit": 0.0,
            "Timestamp": 0.0,
            "Value1": 0.0,
            "Value2": 0.0,
            "Value3": 0.0
        },
        {
            "Action": 0,
            "Bool1": false,
            "ButtonId": 0,
            "Completed": false,
            "Delivered": false,
            "DisplayTime": 5.0,
            "Fault": 0,
            "From": 2,
            "FuseID": 0,
            "FusePosition": 0,
            "KnobID": 0,
            "Message": "In the navigation lesson we will learn how to use the RCS system to control the attitude of the spacecraft.",
            "PinID": 0,
            "PinPosition": 0,
            "String1": null,
            "String2": null,
            "String3": null,
            "ThresholdLimit": 0.0,
            "Timestamp": 0.0,
            "Value1": 0.0,
            "Value2": 0.0,
            "Value3": 0.0
        },
        {
            "Action": 1004,
            "Bool1": false,
            "ButtonId": 0,
            "Completed": false,
            "Delivered": false,
            "DisplayTime": 5.0,
            "Fault": 0,
            "From": 2,
            "FuseID": 0,
            "FusePosition": 0,
            "KnobID": 0,
            "Message": "This completed the RCS lesson!",
            "PinID": 0,
            "PinPosition": 0,
            "String1": null,
            "String2": null,
            "String3": null,
            "ThresholdLimit": 0.0,
            "Timestamp": 0.0,
            "Value1": 0.0,
            "Value2": 0.0,
            "Value3": 0.0
        }
    ],
    "MissionGoals": [
        {
            "Completed": false,
            "Description": "Complete the lesson.",
            "Progress": null,
            "String1": null,
            "String2": null,
            "Target1": 0.0,
            "Target2": 0.0,
            "Target3": 0.0,
            "Type": 0
        }
    ],
    "ScheduledLaunchTime": "1967-06-08T14:00:00",
    "SpaceProgram": 2,
    "StartInOrbit": true,
    "TargetAp": 200.0,
    "TargetPe": 200.0,
    "Title": "Apollo Lesson 4 - RCS"
}