{
  "Rocket": 0,
  "StartInOrbit": false,
  "ScheduledLaunchTime": "1961-07-01T15:00:02",
  "InitialTimeToRetrograde": "00:04:45",
  "MissionCommands": [
    {
      "Delivered": false,
      "Completed": false,
      "Priority": false,
      "Comment": "",
      "ID": "b785b3d9-a7c4-471e-b40b-7c0e9e503ad0",
      "Action": 0,
      "Timestamp": 0.0,
      "DisplayTime": 3.0,
      "From": 1,
      "Message": "Bienvenido de nuevo, {{profileName}}. En esta lección repasaremos todos los pasos necesarios para el lanzamiento, los procedimientos requeridos durante el ascenso y qué monitorear mientras el cohete despega.",
      "Value1": 0.0,
      "Value2": 0.0,
      "Value3": 0.0,
      "String1": "",
      "String2": "",
      "String3": "",
      "Bool1": false,
      "ThresholdLimit": 0.0,
      "PinID": 0,
      "PinPosition": 0,
      "FuseID": 0,
      "PullHandleID": 0,
      "PullHandlePosition": 0,
      "KnobID": 0,
      "ExpButtonID": 0,
      "ButtonID": 0,
      "Fault": 0,
      "Failure": 0,
      "PlayAudioClip_String3": false
    },
    {
      "Delivered": false,
      "Completed": false,
      "Priority": false,
      "Comment": "",
      "ID": "b857a758-a4f3-40ef-b3e7-0cb6fb74fb6b",
      "Action": 0,
      "Timestamp": 25.0,
      "DisplayTime": 6.0,
      "From": 0,
      "Message": "De ahora en adelante, te recomiendo completar cada una de las lecciones de la academia dos veces. Una vez para tener una visión general, y dos veces para profundizar en esa visión general.",
      "Value1": 0.0,
      "Value2": 0.0,
      "Value3": 0.0,
      "String1": "",
      "String2": "",
      "String3": "",
      "Bool1": false,
      "ThresholdLimit": 0.0,
      "PinID": 0,
      "PinPosition": 0,
      "FuseID": 0,
      "PullHandleID": 0,
      "PullHandlePosition": 0,
      "KnobID": 0,
      "ExpButtonID": 0,
      "ButtonID": 0,
      "Fault": 0,
      "Failure": 0,
      "PlayAudioClip_String3": false
    },
    {
      "Delivered": false,
      "Completed": false,
      "Priority": false,
      "Comment": "",
      "ID": "993512b8-3dae-4f8c-a1db-71b8fe821633",
      "Action": 0,
      "Timestamp": 0.0,
      "DisplayTime": 3.0,
      "From": 1,
      "Message": "El ascenso es un proceso automatizado y tu tarea principal es monitorear los instrumentos periódicamente mientras te preparas para un aborto, o para tomar el control manualmente.",
      "Value1": 0.0,
      "Value2": 0.0,
      "Value3": 0.0,
      "String1": "TimeZeroButton",
      "String2": "",
      "String3": "",
      "Bool1": false,
      "ThresholdLimit": 0.0,
      "PinID": 0,
      "PinPosition": 0,
      "FuseID": 0,
      "PullHandleID": 0,
      "PullHandlePosition": 0,
      "KnobID": 0,
      "ExpButtonID": 0,
      "ButtonID": 0,
      "Fault": 0,
      "Failure": 0,
      "PlayAudioClip_String3": false
    },
    {
      "Delivered": false,
      "Completed": false,
      "Priority": false,
      "Comment": "",
      "ID": "c13415e6-11ec-496e-9fa8-1399258447f4",
      "Action": 0,
      "Timestamp": 25.0,
      "DisplayTime": 6.0,
      "From": 1,
      "Message": "Estamos actualmente a 20 minutos de la ignición, con tiempo de sobra para repasar algunos detalles.",
      "Value1": 0.0,
      "Value2": 0.0,
      "Value3": 0.0,
      "String1": "",
      "String2": "",
      "String3": "",
      "Bool1": false,
      "ThresholdLimit": 0.0,
      "PinID": 0,
      "PinPosition": 0,
      "FuseID": 0,
      "PullHandleID": 0,
      "PullHandlePosition": 0,
      "KnobID": 0,
      "ExpButtonID": 0,
      "ButtonID": 0,
      "Fault": 0,
      "Failure": 0,
      "PlayAudioClip_String3": false
    },
    {
      "Delivered": false,
      "Completed": false,
      "Priority": false,
      "Comment": "",
      "ID": "871f1161-a7b6-4582-a994-89fa4f423358",
      "Action": 0,
      "Timestamp": 25.0,
      "DisplayTime": 6.0,
      "From": 1,
      "Message": "Sin embargo, solo para estar seguro, te enseñaré cómo llevar a cabo la cuenta regresiva manualmente. Presiona el botón [C] para alternar las burbujas de función ubicadas en el lado derecho, justo debajo de la sección verde de los paneles.",
      "Value1": 0.0,
      "Value2": 0.0,
      "Value3": 0.0,
      "String1": "",
      "String2": "",
      "String3": "",
      "Bool1": false,
      "ThresholdLimit": 0.0,
      "PinID": 0,
      "PinPosition": 0,
      "FuseID": 0,
      "PullHandleID": 0,
      "PullHandlePosition": 0,
      "KnobID": 0,
      "ExpButtonID": 0,
      "ButtonID": 0,
      "Fault": 0,
      "Failure": 0,
      "PlayAudioClip_String3": false
    },
    {
      "Delivered": false,
      "Completed": false,
      "Priority": false,
      "Comment": "",
      "ID": "645256af-eee3-4acd-81e8-6607cacffd52",
      "Action": 505,
      "Timestamp": 25.0,
      "DisplayTime": 6.0,
      "From": 1,
      "Message": "Localiza y encuentra la burbuja de la función de CUENTA REGRESIVA DE RETENCIÓN, y haz clic en ella.",
      "Value1": 0.0,
      "Value2": 0.0,
      "Value3": 0.0,
      "String1": "",
      "String2": "",
      "String3": "",
      "Bool1": true,
      "ThresholdLimit": 0.0,
      "PinID": 0,
      "PinPosition": 0,
      "FuseID": 0,
      "PullHandleID": 0,
      "PullHandlePosition": 0,
      "KnobID": 0,
      "ExpButtonID": 0,
      "ButtonID": 0,
      "Fault": 0,
      "Failure": 0,
      "PlayAudioClip_String3": false
    },
    {
      "Delivered": false,
      "Completed": false,
      "Priority": false,
      "Comment": "",
      "ID": "f893a114-7aa8-4a54-ac5c-6dd5944bef2e",
      "Action": 1,
      "Timestamp": 0.0,
      "DisplayTime": 3.0,
      "From": 1,
      "Message": "¡Excelente, la cuenta regresiva ya está en marcha!",
      "Value1": 0.0,
      "Value2": 0.0,
      "Value3": 0.0,
      "String1": "",
      "String2": "",
      "String3": "",
      "Bool1": false,
      "ThresholdLimit": 0.0,
      "PinID": 0,
      "PinPosition": 0,
      "FuseID": 0,
      "PullHandleID": 0,
      "PullHandlePosition": 0,
      "KnobID": 0,
      "ExpButtonID": 0,
      "ButtonID": 0,
      "Fault": 0,
      "Failure": 0,
      "PlayAudioClip_String3": false
    },
    {
      "Delivered": false,
      "Completed": false,
      "Priority": false,
      "Comment": "",
      "ID": "12a20a18-207d-4367-838d-85495aacf065",
      "Action": 0,
      "Timestamp": 25.0,
      "DisplayTime": 6.0,
      "From": 1,
      "Message": "Los paneles de la cabina están en su configuración final previa al lanzamiento, con solo unos pocos interruptores restantes por ajustar.",
      "Value1": 0.0,
      "Value2": 0.0,
      "Value3": 0.0,
      "String1": "",
      "String2": "",
      "String3": "",
      "Bool1": false,
      "ThresholdLimit": 0.0,
      "PinID": 0,
      "PinPosition": 0,
      "FuseID": 0,
      "PullHandleID": 0,
      "PullHandlePosition": 0,
      "KnobID": 0,
      "ExpButtonID": 0,
      "ButtonID": 0,
      "Fault": 0,
      "Failure": 0,
      "PlayAudioClip_String3": false
    },
    {
      "Delivered": false,
      "Completed": false,
      "Priority": false,
      "Comment": "",
      "ID": "7516a0bd-4ff4-4e3f-a186-1a47032be662",
      "Action": 1,
      "Timestamp": 25.0,
      "DisplayTime": 6.0,
      "From": 1,
      "Message": "Abramos el PAD DE MISIÓN. Presiona [M] para activarlo, y luego presiona la pestaña de LISTAS DE VERIFICACIÓN. Presiona ROGER cuando lo tengas abierto.",
      "Value1": 0.0,
      "Value2": 0.0,
      "Value3": 0.0,
      "String1": "",
      "String2": "",
      "String3": "",
      "Bool1": false,
      "ThresholdLimit": 0.0,
      "PinID": 0,
      "PinPosition": 0,
      "FuseID": 0,
      "PullHandleID": 0,
      "PullHandlePosition": 0,
      "KnobID": 0,
      "ExpButtonID": 0,
      "ButtonID": 0,
      "Fault": 0,
      "Failure": 0,
      "PlayAudioClip_String3": false
    },
    {
      "Delivered": false,
      "Completed": false,
      "Priority": false,
      "Comment": "",
      "ID": "a55df8a1-b909-47ef-a342-127b28809970",
      "Action": 1,
      "Timestamp": 25.0,
      "DisplayTime": 6.0,
      "From": 1,
      "Message": "La pestaña de LISTA DE VERIFICACIÓN del MISSION PAD contiene todas las listas de verificación de Mercury necesarias durante una misión. Actualmente tenemos dos listas de verificación para completar antes de que podamos ascender, la DE ENERGÍA INTERNA COMPLETA y la DE VERIFICACIONES FINALES.",
      "Value1": 0.0,
      "Value2": 0.0,
      "Value3": 0.0,
      "String1": "",
      "String2": "",
      "String3": "",
      "Bool1": false,
      "ThresholdLimit": 0.0,
      "PinID": 0,
      "PinPosition": 0,
      "FuseID": 0,
      "PullHandleID": 0,
      "PullHandlePosition": 0,
      "KnobID": 0,
      "ExpButtonID": 0,
      "ButtonID": 0,
      "Fault": 0,
      "Failure": 0,
      "PlayAudioClip_String3": false
    },
    {
      "Delivered": false,
      "Completed": false,
      "Priority": false,
      "Comment": "",
      "ID": "cfad7aef-4ce2-40e1-999d-fd4fb7d550c8",
      "Action": 1,
      "Timestamp": 25.0,
      "DisplayTime": 6.0,
      "From": 1,
      "Message": "Esta lección te guiará a través de todos los pasos necesarios para que puedas presionar [M] para desactivar nuevamente el Panel de Misión. En la próxima lección, aprenderemos más al respecto, y algunas características del sistema de lista de verificación que nos permitirá ejecutar listas de verificación.",
      "Value1": 0.0,
      "Value2": 0.0,
      "Value3": 0.0,
      "String1": "",
      "String2": "",
      "String3": "",
      "Bool1": false,
      "ThresholdLimit": 0.0,
      "PinID": 0,
      "PinPosition": 0,
      "FuseID": 0,
      "PullHandleID": 0,
      "PullHandlePosition": 0,
      "KnobID": 0,
      "ExpButtonID": 0,
      "ButtonID": 0,
      "Fault": 0,
      "Failure": 0,
      "PlayAudioClip_String3": false
    },
    {
      "Delivered": false,
      "Completed": false,
      "Priority": false,
      "Comment": "",
      "ID": "824077a0-ea87-4412-a3e7-9efafac05819",
      "Action": 0,
      "Timestamp": 25.0,
      "DisplayTime": 6.0,
      "From": 1,
      "Message": "Estamos actualmente realizando la cuenta regresiva pero típicamente, alrededor de 10 minutos antes del despegue, a menudo referido como T -10 minutos, la fuente de energía se cambia de energía externa a energía interna.",
      "Value1": 0.0,
      "Value2": 0.0,
      "Value3": 0.0,
      "String1": "",
      "String2": "",
      "String3": "",
      "Bool1": false,
      "ThresholdLimit": 0.0,
      "PinID": 0,
      "PinPosition": 0,
      "FuseID": 0,
      "PullHandleID": 0,
      "PullHandlePosition": 0,
      "KnobID": 0,
      "ExpButtonID": 0,
      "ButtonID": 0,
      "Fault": 0,
      "Failure": 0,
      "PlayAudioClip_String3": false
    },
    {
      "Delivered": false,
      "Completed": false,
      "Priority": false,
      "Comment": "",
      "ID": "bfa7d342-30a8-4b2b-b777-dfa17ac483b1",
      "Action": 0,
      "Timestamp": 25.0,
      "DisplayTime": 6.0,
      "From": 1,
      "Message": "El cohete está actualmente recibiendo energía a través de un cordón umbilical conectado a la plataforma de lanzamiento. Esto es para evitar consumir energía del sistema de energía interno (baterías) antes de que la misión comience siquiera.",
      "Value1": 0.0,
      "Value2": 0.0,
      "Value3": 0.0,
      "String1": "",
      "String2": "",
      "String3": "",
      "Bool1": false,
      "ThresholdLimit": 0.0,
      "PinID": 0,
      "PinPosition": 0,
      "FuseID": 0,
      "PullHandleID": 0,
      "PullHandlePosition": 0,
      "KnobID": 0,
      "ExpButtonID": 0,
      "ButtonID": 0,
      "Fault": 0,
      "Failure": 0,
      "PlayAudioClip_String3": false
    },
    {
      "Delivered": false,
      "Completed": false,
      "Priority": false,
      "Comment": "",
      "ID": "5ebe1295-8268-4044-b51b-7012f3bfbc13",
      "Action": 0,
      "Timestamp": 25.0,
      "DisplayTime": 6.0,
      "From": 1,
      "Message": "Eche un vistazo a los paneles frente a usted, e intente localizar el medidor de CC AMPERIOS. Está en el lado derecho del periscopio. Presione ROGER para resaltarlo.",
      "Value1": 0.0,
      "Value2": 0.0,
      "Value3": 0.0,
      "String1": "",
      "String2": "",
      "String3": "",
      "Bool1": false,
      "ThresholdLimit": 0.0,
      "PinID": 0,
      "PinPosition": 0,
      "FuseID": 0,
      "PullHandleID": 0,
      "PullHandlePosition": 0,
      "KnobID": 0,
      "ExpButtonID": 0,
      "ButtonID": 0,
      "Fault": 0,
      "Failure": 0,
      "PlayAudioClip_String3": false
    },
    {
      "Delivered": false,
      "Completed": false,
      "Priority": false,
      "Comment": "",
      "ID": "dd723e78-324b-4614-ab03-1f2a1d088837",
      "Action": 106,
      "Timestamp": 25.0,
      "DisplayTime": 10.0,
      "From": 1,
      "Message": "Este es el medidor de AMPS DC. Muestra el consumo actual en amperios del sistema de energía interno.",
      "Value1": 0.0,
      "Value2": 0.0,
      "Value3": 0.0,
      "String1": "GaugeSteamDCAmps",
      "String2": "",
      "String3": "",
      "Bool1": false,
      "ThresholdLimit": 0.0,
      "PinID": 0,
      "PinPosition": 0,
      "FuseID": 0,
      "PullHandleID": 0,
      "PullHandlePosition": 0,
      "KnobID": 0,
      "ExpButtonID": 0,
      "ButtonID": 0,
      "Fault": 0,
      "Failure": 0,
      "PlayAudioClip_String3": false
    },
    {
      "Delivered": false,
      "Completed": false,
      "Priority": false,
      "Comment": "",
      "ID": "6e60fbcf-bff3-48ed-a68f-ac9ef51379bf",
      "Action": 106,
      "Timestamp": 25.0,
      "DisplayTime": 6.0,
      "From": 1,
      "Message": "En el lado izquierdo del medidor de DC AMPERIOS puedes encontrar el medidor de VOLTIOS de DC.",
      "Value1": 0.0,
      "Value2": 0.0,
      "Value3": 0.0,
      "String1": "GaugeSteamDCVolts",
      "String2": "",
      "String3": "",
      "Bool1": false,
      "ThresholdLimit": 0.0,
      "PinID": 0,
      "PinPosition": 0,
      "FuseID": 0,
      "PullHandleID": 0,
      "PullHandlePosition": 0,
      "KnobID": 0,
      "ExpButtonID": 0,
      "ButtonID": 0,
      "Fault": 0,
      "Failure": 0,
      "PlayAudioClip_String3": false
    },
    {
      "Delivered": false,
      "Completed": false,
      "Priority": false,
      "Comment": "",
      "ID": "473dbcba-53b0-4c46-8fa9-c1904af46ae8",
      "Action": 0,
      "Timestamp": 25.0,
      "DisplayTime": 6.0,
      "From": 1,
      "Message": "Esto muestra los VOLTIOS DE CC del sistema de energía interno. ",
      "Value1": 0.0,
      "Value2": 0.0,
      "Value3": 0.0,
      "String1": "",
      "String2": "",
      "String3": "",
      "Bool1": false,
      "ThresholdLimit": 0.0,
      "PinID": 0,
      "PinPosition": 0,
      "FuseID": 0,
      "PullHandleID": 0,
      "PullHandlePosition": 0,
      "KnobID": 0,
      "ExpButtonID": 0,
      "ButtonID": 0,
      "Fault": 0,
      "Failure": 0,
      "PlayAudioClip_String3": false
    },
    {
      "Delivered": false,
      "Completed": false,
      "Priority": false,
      "Comment": "",
      "ID": "464b62b4-311c-4401-b139-e84052df69e2",
      "Action": 103,
      "Timestamp": 25.0,
      "DisplayTime": 6.0,
      "From": 1,
      "Message": "Debajo de los dos medidores, puedes encontrar el selector de CC. Este se utiliza para seleccionar qué está mostrando el medidor de VOLTIOS CC y AMPERIOS CC. Ajusta esto a 1 haciendo clic izquierdo en él.",
      "Value1": 1.0,
      "Value2": 0.0,
      "Value3": 0.0,
      "String1": "",
      "String2": "",
      "String3": "",
      "Bool1": false,
      "ThresholdLimit": 0.0,
      "PinID": 0,
      "PinPosition": 0,
      "FuseID": 0,
      "PullHandleID": 0,
      "PullHandlePosition": 0,
      "KnobID": 1,
      "ExpButtonID": 0,
      "ButtonID": 0,
      "Fault": 0,
      "Failure": 0,
      "PlayAudioClip_String3": false
    },
    {
      "Delivered": false,
      "Completed": false,
      "Priority": false,
      "Comment": "",
      "ID": "477a9734-1a64-45e2-ba33-31b1c4e114f5",
      "Action": 1,
      "Timestamp": 25.0,
      "DisplayTime": 6.0,
      "From": 1,
      "Message": "El medidor de amperios de corriente continua (DC AMPS) y el medidor de voltios de corriente continua (DC VOLTS) ahora muestran los voltios actuales de la batería 1 y la carga actual en la batería 1.",
      "Value1": 0.0,
      "Value2": 0.0,
      "Value3": 0.0,
      "String1": "",
      "String2": "",
      "String3": "",
      "Bool1": false,
      "ThresholdLimit": 0.0,
      "PinID": 0,
      "PinPosition": 0,
      "FuseID": 0,
      "PullHandleID": 0,
      "PullHandlePosition": 0,
      "KnobID": 0,
      "ExpButtonID": 0,
      "ButtonID": 0,
      "Fault": 0,
      "Failure": 0,
      "PlayAudioClip_String3": false
    },
    {
      "Delivered": false,
      "Completed": false,
      "Priority": false,
      "Comment": "",
      "ID": "7499fa50-b18e-4f2d-b65e-ff26ba317a7c",
      "Action": 1,
      "Timestamp": 25.0,
      "DisplayTime": 6.0,
      "From": 1,
      "Message": "El bloque de control (una casa que controla el lanzamiento ubicada en el complejo de lanzamiento actual) cambiará pronto a energía interna. Durante la transición de energía, es importante monitorear el medidor de AMPERIOS DC y VOLTIOS DC.",
      "Value1": 0.0,
      "Value2": 0.0,
      "Value3": 0.0,
      "String1": "",
      "String2": "",
      "String3": "",
      "Bool1": false,
      "ThresholdLimit": 0.0,
      "PinID": 0,
      "PinPosition": 0,
      "FuseID": 0,
      "PullHandleID": 0,
      "PullHandlePosition": 0,
      "KnobID": 0,
      "ExpButtonID": 0,
      "ButtonID": 0,
      "Fault": 0,
      "Failure": 0,
      "PlayAudioClip_String3": false
    },
    {
      "Delivered": false,
      "Completed": false,
      "Priority": false,
      "Comment": "",
      "ID": "b420052e-fe29-4e92-a941-d5b6c0211359",
      "Action": 103,
      "Timestamp": 25.0,
      "DisplayTime": 6.0,
      "From": 1,
      "Message": "Establece el DC SELECTOR de nuevo en M haciendo clic derecho una vez en él. Esto supervisa el bus eléctrico principal de las cápsulas (más sobre esto en la lección del sistema eléctrico de potencia).",
      "Value1": 0.0,
      "Value2": 0.0,
      "Value3": 0.0,
      "String1": "",
      "String2": "",
      "String3": "",
      "Bool1": false,
      "ThresholdLimit": 0.0,
      "PinID": 0,
      "PinPosition": 0,
      "FuseID": 0,
      "PullHandleID": 0,
      "PullHandlePosition": 0,
      "KnobID": 1,
      "ExpButtonID": 0,
      "ButtonID": 0,
      "Fault": 0,
      "Failure": 0,
      "PlayAudioClip_String3": false
    },
    {
      "Delivered": false,
      "Completed": false,
      "Priority": false,
      "Comment": "",
      "ID": "ad3da4ee-ebb4-4e22-83e9-5998da40d89f",
      "Action": 1,
      "Timestamp": 25.0,
      "DisplayTime": 6.0,
      "From": 1,
      "Message": "Ahora, observa los AMPERIOS de CC y los VOLTIOS de CC mientras presionas ROGER para hacerle saber a la casamata que estás listo para cambiar a la energía interna.",
      "Value1": 0.0,
      "Value2": 0.0,
      "Value3": 0.0,
      "String1": "",
      "String2": "",
      "String3": "",
      "Bool1": false,
      "ThresholdLimit": 0.0,
      "PinID": 0,
      "PinPosition": 0,
      "FuseID": 0,
      "PullHandleID": 0,
      "PullHandlePosition": 0,
      "KnobID": 0,
      "ExpButtonID": 0,
      "ButtonID": 0,
      "Fault": 0,
      "Failure": 0,
      "PlayAudioClip_String3": false
    },
    {
      "Delivered": false,
      "Completed": false,
      "Priority": false,
      "Comment": "",
      "ID": "fb702213-5073-41e6-8101-f73c857d4178",
      "Action": 84,
      "Timestamp": 25.0,
      "DisplayTime": 6.0,
      "From": 1,
      "Message": "",
      "Value1": 0.0,
      "Value2": 0.0,
      "Value3": 0.0,
      "String1": "",
      "String2": "",
      "String3": "",
      "Bool1": false,
      "ThresholdLimit": 0.0,
      "PinID": 0,
      "PinPosition": 0,
      "FuseID": 0,
      "PullHandleID": 0,
      "PullHandlePosition": 0,
      "KnobID": 0,
      "ExpButtonID": 0,
      "ButtonID": 0,
      "Fault": 0,
      "Failure": 0,
      "PlayAudioClip_String3": false
    },
    {
      "Delivered": false,
      "Completed": false,
      "Priority": false,
      "Comment": "",
      "ID": "34a2c011-1b37-4040-b524-a28c81775074",
      "Action": 0,
      "Timestamp": 25.0,
      "DisplayTime": 6.0,
      "From": 1,
      "Message": "Excelente. El bus principal ahora está manejando la carga de todo el equipo a bordo. El voltaje del bus principal debería estar alrededor de 23-27 voltios con un consumo de 20-40 amperios.",
      "Value1": 0.0,
      "Value2": 0.0,
      "Value3": 0.0,
      "String1": "",
      "String2": "",
      "String3": "",
      "Bool1": false,
      "ThresholdLimit": 0.0,
      "PinID": 0,
      "PinPosition": 0,
      "FuseID": 0,
      "PullHandleID": 0,
      "PullHandlePosition": 0,
      "KnobID": 0,
      "ExpButtonID": 0,
      "ButtonID": 0,
      "Fault": 0,
      "Failure": 0,
      "PlayAudioClip_String3": false
    },
    {
      "Delivered": false,
      "Completed": false,
      "Priority": false,
      "Comment": "",
      "ID": "cfef5ace-7698-49e7-bcf1-ed678c609b74",
      "Action": 103,
      "Timestamp": 25.0,
      "DisplayTime": 6.0,
      "From": 1,
      "Message": "Has revisado ahora el voltaje y las cargas del bus PRINCIPAL. Vamos a chequear la carga de la batería 1. Ajusta el SELECCIONADOR DC a 1. Esto significa Batería 1.",
      "Value1": 1.0,
      "Value2": 0.0,
      "Value3": 0.0,
      "String1": "",
      "String2": "",
      "String3": "",
      "Bool1": false,
      "ThresholdLimit": 0.0,
      "PinID": 0,
      "PinPosition": 0,
      "FuseID": 0,
      "PullHandleID": 0,
      "PullHandlePosition": 0,
      "KnobID": 1,
      "ExpButtonID": 0,
      "ButtonID": 0,
      "Fault": 0,
      "Failure": 0,
      "PlayAudioClip_String3": false
    },
    {
      "Delivered": false,
      "Completed": false,
      "Priority": false,
      "Comment": "",
      "ID": "271b2c47-ec28-480c-af0b-c311a428289a",
      "Action": 103,
      "Timestamp": 25.0,
      "DisplayTime": 6.0,
      "From": 1,
      "Message": "El texto traducido al español con los corchetes sería: Debería leer alrededor de 23-27 voltios y 10-20 amperios. Verifique también la batería N.º 2.",
      "Value1": 2.0,
      "Value2": 0.0,
      "Value3": 0.0,
      "String1": "",
      "String2": "",
      "String3": "",
      "Bool1": false,
      "ThresholdLimit": 0.0,
      "PinID": 0,
      "PinPosition": 0,
      "FuseID": 0,
      "PullHandleID": 0,
      "PullHandlePosition": 0,
      "KnobID": 1,
      "ExpButtonID": 0,
      "ButtonID": 0,
      "Fault": 0,
      "Failure": 0,
      "PlayAudioClip_String3": false
    },
    {
      "Delivered": false,
      "Completed": false,
      "Priority": false,
      "Comment": "",
      "ID": "c5423859-e71f-4acb-94b8-43aa3f039f7c",
      "Action": 103,
      "Timestamp": 25.0,
      "DisplayTime": 6.0,
      "From": 1,
      "Message": "Claro, también debería mostrar alrededor de 23-27 voltios y entre 10 y 20 amperios. Verificar también la batería No. 3.",
      "Value1": 3.0,
      "Value2": 0.0,
      "Value3": 0.0,
      "String1": "",
      "String2": "",
      "String3": "",
      "Bool1": false,
      "ThresholdLimit": 0.0,
      "PinID": 0,
      "PinPosition": 0,
      "FuseID": 0,
      "PullHandleID": 0,
      "PullHandlePosition": 0,
      "KnobID": 1,
      "ExpButtonID": 0,
      "ButtonID": 0,
      "Fault": 0,
      "Failure": 0,
      "PlayAudioClip_String3": false
    },
    {
      "Delivered": false,
      "Completed": false,
      "Priority": false,
      "Comment": "",
      "ID": "72b432fa-bbc2-474e-aa8b-0dba29517366",
      "Action": 103,
      "Timestamp": 25.0,
      "DisplayTime": 6.0,
      "From": 1,
      "Message": "Los SBY 1, SBY 2 e ISO actualmente no tienen cargas, por lo que los amperios deberían ser cero, sin embargo, deberían tener voltios. Verifiquemos. Establece el SELECTOR DE CC en SBY 1.",
      "Value1": 4.0,
      "Value2": 0.0,
      "Value3": 0.0,
      "String1": "",
      "String2": "",
      "String3": "",
      "Bool1": false,
      "ThresholdLimit": 0.0,
      "PinID": 0,
      "PinPosition": 0,
      "FuseID": 0,
      "PullHandleID": 0,
      "PullHandlePosition": 0,
      "KnobID": 1,
      "ExpButtonID": 0,
      "ButtonID": 0,
      "Fault": 0,
      "Failure": 0,
      "PlayAudioClip_String3": false
    },
    {
      "Delivered": false,
      "Completed": false,
      "Priority": false,
      "Comment": "",
      "ID": "ab91ccee-5fcc-474b-8e36-b3dada54c008",
      "Action": 103,
      "Timestamp": 25.0,
      "DisplayTime": 6.0,
      "From": 1,
      "Message": "SBY 1 representa Batería de Reserva 1, una de nuestras dos baterías de sistema de respaldo. Verifique que su voltaje esté entre 23 y 27 voltios, luego ajuste el SELECCIONADOR DE CC a SBY 2.",
      "Value1": 5.0,
      "Value2": 0.0,
      "Value3": 0.0,
      "String1": "",
      "String2": "",
      "String3": "",
      "Bool1": false,
      "ThresholdLimit": 0.0,
      "PinID": 0,
      "PinPosition": 0,
      "FuseID": 0,
      "PullHandleID": 0,
      "PullHandlePosition": 0,
      "KnobID": 1,
      "ExpButtonID": 0,
      "ButtonID": 0,
      "Fault": 0,
      "Failure": 0,
      "PlayAudioClip_String3": false
    },
    {
      "Delivered": false,
      "Completed": false,
      "Priority": false,
      "Comment": "",
      "ID": "224e5c52-b122-492c-a00f-82f3976a76f4",
      "Action": 103,
      "Timestamp": 25.0,
      "DisplayTime": 6.0,
      "From": 1,
      "Message": "SBY 2 representa Batería de Reserva 2, una de nuestras dos baterías del sistema de respaldo. Verifique que su voltaje esté entre 23 y 27 vcc. Luego, configure el SELECTOR DE CC en ISO.",
      "Value1": 6.0,
      "Value2": 0.0,
      "Value3": 0.0,
      "String1": "",
      "String2": "",
      "String3": "",
      "Bool1": false,
      "ThresholdLimit": 0.0,
      "PinID": 0,
      "PinPosition": 0,
      "FuseID": 0,
      "PullHandleID": 0,
      "PullHandlePosition": 0,
      "KnobID": 1,
      "ExpButtonID": 0,
      "ButtonID": 0,
      "Fault": 0,
      "Failure": 0,
      "PlayAudioClip_String3": false
    },
    {
      "Delivered": false,
      "Completed": false,
      "Priority": false,
      "Comment": "",
      "ID": "8020ac32-b680-426d-96a9-694e91dfcb5f",
      "Action": 103,
      "Timestamp": 25.0,
      "DisplayTime": 6.0,
      "From": 1,
      "Message": "ISO significa Isolated Battery y se usa principalmente para alimentar algo llamado los SQUIBs. Cubriremos los SQUIBs más adelante. Por ahora, asegúrese de que la batería ISOlada tenga un voltaje de 29 vdc. Coloque el DC SELECTOR de nuevo en la posición MAIN.",
      "Value1": 0.0,
      "Value2": 0.0,
      "Value3": 0.0,
      "String1": "",
      "String2": "",
      "String3": "",
      "Bool1": false,
      "ThresholdLimit": 0.0,
      "PinID": 0,
      "PinPosition": 0,
      "FuseID": 0,
      "PullHandleID": 0,
      "PullHandlePosition": 0,
      "KnobID": 1,
      "ExpButtonID": 0,
      "ButtonID": 0,
      "Fault": 0,
      "Failure": 0,
      "PlayAudioClip_String3": false
    },
    {
      "Delivered": false,
      "Completed": false,
      "Priority": false,
      "Comment": "",
      "ID": "9c175869-8c0f-4e71-b3bb-418d1084e61c",
      "Action": 0,
      "Timestamp": 25.0,
      "DisplayTime": 6.0,
      "From": 1,
      "Message": "Excelente, ahora hemos realizado una verificación completa del autobús eléctrico después del cambio a la alimentación interna, todo se ve bien. Esto también es algo que debes hacer periódicamente durante el ascenso, preferiblemente cada 30 segundos.",
      "Value1": 0.0,
      "Value2": 0.0,
      "Value3": 0.0,
      "String1": "",
      "String2": "",
      "String3": "",
      "Bool1": false,
      "ThresholdLimit": 0.0,
      "PinID": 0,
      "PinPosition": 0,
      "FuseID": 0,
      "PullHandleID": 0,
      "PullHandlePosition": 0,
      "KnobID": 0,
      "ExpButtonID": 0,
      "ButtonID": 0,
      "Fault": 0,
      "Failure": 0,
      "PlayAudioClip_String3": false
    },
    {
      "Delivered": false,
      "Completed": false,
      "Priority": false,
      "Comment": "",
      "ID": "ab678cef-becc-4399-8de1-2ebb57dddfef",
      "Action": 0,
      "Timestamp": 25.0,
      "DisplayTime": 6.0,
      "From": 1,
      "Message": "El \"Cambio a Energía Interna Completa\" debería ocurrir 10 minutos antes del encendido para evitar un consumo excesivo de la batería crítica de la misión. ¡No queremos quedarnos sin energía en el espacio!",
      "Value1": 0.0,
      "Value2": 0.0,
      "Value3": 0.0,
      "String1": "",
      "String2": "",
      "String3": "",
      "Bool1": false,
      "ThresholdLimit": 0.0,
      "PinID": 0,
      "PinPosition": 0,
      "FuseID": 0,
      "PullHandleID": 0,
      "PullHandlePosition": 0,
      "KnobID": 0,
      "ExpButtonID": 0,
      "ButtonID": 0,
      "Fault": 0,
      "Failure": 0,
      "PlayAudioClip_String3": false
    },
    {
      "Delivered": false,
      "Completed": false,
      "Priority": false,
      "Comment": "",
      "ID": "5d563270-f4b1-4699-8212-3c317a00ee07",
      "Action": 505,
      "Timestamp": 25.0,
      "DisplayTime": 6.0,
      "From": 1,
      "Message": "Ahora te enseñaré cómo REANUDAR la CUENTA REGRESIVA nuevamente. Presiona [C] para alternar las burbujas de función y encuentra el botón REANUDAR CUENTA REGRESIVA, luego presiónalo para reanudar la cuenta regresiva.",
      "Value1": 0.0,
      "Value2": 0.0,
      "Value3": 0.0,
      "String1": "",
      "String2": "",
      "String3": "",
      "Bool1": false,
      "ThresholdLimit": 0.0,
      "PinID": 0,
      "PinPosition": 0,
      "FuseID": 0,
      "PullHandleID": 0,
      "PullHandlePosition": 0,
      "KnobID": 0,
      "ExpButtonID": 0,
      "ButtonID": 0,
      "Fault": 0,
      "Failure": 0,
      "PlayAudioClip_String3": false
    },
    {
      "Delivered": false,
      "Completed": false,
      "Priority": false,
      "Comment": "",
      "ID": "1937886a-c2dd-4fe5-b030-a97a5cadfec2",
      "Action": 0,
      "Timestamp": 25.0,
      "DisplayTime": 6.0,
      "From": 1,
      "Message": "Puedes usar las teclas alfa para escalar el tiempo. A continuación, usaremos el [1] (tiempo normal), [2] (escala de tiempo 2 veces más rápido), [3] (escala de tiempo 5 veces más rápido), etc. para escalar el tiempo a T -5 minutos antes del lanzamiento.",
      "Value1": 0.0,
      "Value2": 0.0,
      "Value3": 0.0,
      "String1": "",
      "String2": "",
      "String3": "",
      "Bool1": false,
      "ThresholdLimit": 0.0,
      "PinID": 0,
      "PinPosition": 0,
      "FuseID": 0,
      "PullHandleID": 0,
      "PullHandlePosition": 0,
      "KnobID": 0,
      "ExpButtonID": 0,
      "ButtonID": 0,
      "Fault": 0,
      "Failure": 0,
      "PlayAudioClip_String3": false
    },
    {
      "Delivered": false,
      "Completed": false,
      "Priority": false,
      "Comment": "",
      "ID": "731718eb-fd03-4326-8664-09ed0d467106",
      "Action": 0,
      "Timestamp": 25.0,
      "DisplayTime": 6.0,
      "From": 1,
      "Message": "Normalmente se usa la escala de tiempo para reducir el tiempo de espera. La función está disponible durante una misión, excepto durante fases críticas o potenciadas de la misión, como el ascenso y el reingreso. Siempre puedes presionar [0] para pausar el juego. Intenta ajustar la escala de tiempo a 2x presionando [2], luego [1] para regresar.",
      "Value1": 0.0,
      "Value2": 0.0,
      "Value3": 0.0,
      "String1": "",
      "String2": "",
      "String3": "",
      "Bool1": false,
      "ThresholdLimit": 0.0,
      "PinID": 0,
      "PinPosition": 0,
      "FuseID": 0,
      "PullHandleID": 0,
      "PullHandlePosition": 0,
      "KnobID": 0,
      "ExpButtonID": 0,
      "ButtonID": 0,
      "Fault": 0,
      "Failure": 0,
      "PlayAudioClip_String3": false
    },
    {
      "Delivered": false,
      "Completed": false,
      "Priority": false,
      "Comment": "",
      "ID": "d3705e56-9219-408c-85ad-c58756a2ef85",
      "Action": 0,
      "Timestamp": 25.0,
      "DisplayTime": 6.0,
      "From": 1,
      "Message": "Escala de tiempo a T -5 minutos. Evita usar más de [5] (escala de tiempo 20 veces mayor) en la plataforma de lanzamiento, ya que podrías pasar por alto pasos importantes.",
      "Value1": 0.0,
      "Value2": 0.0,
      "Value3": 0.0,
      "String1": "",
      "String2": "",
      "String3": "",
      "Bool1": false,
      "ThresholdLimit": 0.0,
      "PinID": 0,
      "PinPosition": 0,
      "FuseID": 0,
      "PullHandleID": 0,
      "PullHandlePosition": 0,
      "KnobID": 0,
      "ExpButtonID": 0,
      "ButtonID": 0,
      "Fault": 0,
      "Failure": 0,
      "PlayAudioClip_String3": false
    },
    {
      "Delivered": false,
      "Completed": false,
      "Priority": false,
      "Comment": "",
      "ID": "185ce67d-7d43-4d4a-955b-fd9082bd0b2d",
      "Action": 506,
      "Timestamp": 900.0,
      "DisplayTime": 6.0,
      "From": 1,
      "Message": "He realizado ahora una RETENCIÓN automática de la cuenta regresiva para asegurarnos de que tengamos suficiente tiempo.",
      "Value1": 0.0,
      "Value2": 0.0,
      "Value3": 0.0,
      "String1": "",
      "String2": "",
      "String3": "",
      "Bool1": false,
      "ThresholdLimit": 0.0,
      "PinID": 0,
      "PinPosition": 0,
      "FuseID": 0,
      "PullHandleID": 0,
      "PullHandlePosition": 0,
      "KnobID": 0,
      "ExpButtonID": 0,
      "ButtonID": 0,
      "Fault": 0,
      "Failure": 0,
      "PlayAudioClip_String3": false
    },
    {
      "Delivered": false,
      "Completed": false,
      "Priority": false,
      "Comment": "",
      "ID": "b0b02af3-36d8-4341-929c-4a71131d3390",
      "Action": 0,
      "Timestamp": 25.0,
      "DisplayTime": 6.0,
      "From": 1,
      "Message": "En otras palabras, realicemos las verificaciones FINALES necesarias para completar las configuraciones de la cápsula previas al lanzamiento, preparándonos para el ascenso.",
      "Value1": 0.0,
      "Value2": 0.0,
      "Value3": 0.0,
      "String1": "",
      "String2": "",
      "String3": "",
      "Bool1": false,
      "ThresholdLimit": 0.0,
      "PinID": 0,
      "PinPosition": 0,
      "FuseID": 0,
      "PullHandleID": 0,
      "PullHandlePosition": 0,
      "KnobID": 0,
      "ExpButtonID": 0,
      "ButtonID": 0,
      "Fault": 0,
      "Failure": 0,
      "PlayAudioClip_String3": false
    },
    {
      "Delivered": false,
      "Completed": false,
      "Priority": false,
      "Comment": "",
      "ID": "efce61f0-e79c-4891-bc52-20193f6752b6",
      "Action": 100,
      "Timestamp": 0.0,
      "DisplayTime": 3.0,
      "From": 1,
      "Message": "Indiquemos al Búnker que estamos iniciando las verificaciones finales y estaremos listos para el lanzamiento. Coloca el interruptor de CONTROL DE LANZAMIENTO en LISTO para que el búnker sepa que pueden activar la ignición. Si este interruptor está en LISTO, el cohete se lanzará cuando la cuenta regresiva llegue a cero.",
      "Value1": 0.0,
      "Value2": 0.0,
      "Value3": 0.0,
      "String1": "",
      "String2": "",
      "String3": "",
      "Bool1": false,
      "ThresholdLimit": 0.0,
      "PinID": 3,
      "PinPosition": 1,
      "FuseID": 0,
      "PullHandleID": 0,
      "PullHandlePosition": 0,
      "KnobID": 0,
      "ExpButtonID": 0,
      "ButtonID": 0,
      "Fault": 0,
      "Failure": 0,
      "PlayAudioClip_String3": false
    },
    {
      "Delivered": false,
      "Completed": false,
      "Priority": false,
      "Comment": "",
      "ID": "9dbef234-4e40-4b83-a3d3-7269af24a97e",
      "Action": 106,
      "Timestamp": 25.0,
      "DisplayTime": 10.0,
      "From": 1,
      "Message": "Verifica que el selector de TEMPERATURA DE TRAJE esté en la posición 3 (un triángulo MARCA esta posición predeterminada de ascenso).",
      "Value1": 0.0,
      "Value2": 0.0,
      "Value3": 0.0,
      "String1": "SuitTemp",
      "String2": "",
      "String3": "",
      "Bool1": false,
      "ThresholdLimit": 0.0,
      "PinID": 0,
      "PinPosition": 0,
      "FuseID": 0,
      "PullHandleID": 0,
      "PullHandlePosition": 0,
      "KnobID": 0,
      "ExpButtonID": 0,
      "ButtonID": 0,
      "Fault": 0,
      "Failure": 0,
      "PlayAudioClip_String3": false
    },
    {
      "Delivered": false,
      "Completed": false,
      "Priority": false,
      "Comment": "",
      "ID": "70812c92-eb25-4be4-ba62-c268c8a2d0bf",
      "Action": 106,
      "Timestamp": 25.0,
      "DisplayTime": 6.0,
      "From": 1,
      "Message": "Verifique que el selector de TEMPERATURA DE LA CABINA esté configurado en la posición 3 también (una marca triangular SEÑALA esta posición de ascenso predeterminada).",
      "Value1": 0.0,
      "Value2": 0.0,
      "Value3": 0.0,
      "String1": "CabinTemp",
      "String2": "",
      "String3": "",
      "Bool1": false,
      "ThresholdLimit": 0.0,
      "PinID": 0,
      "PinPosition": 0,
      "FuseID": 0,
      "PullHandleID": 0,
      "PullHandlePosition": 0,
      "KnobID": 0,
      "ExpButtonID": 0,
      "ButtonID": 0,
      "Fault": 0,
      "Failure": 0,
      "PlayAudioClip_String3": false
    },
    {
      "Delivered": false,
      "Completed": false,
      "Priority": false,
      "Comment": "",
      "ID": "f2a8afb5-7c19-410b-9c3e-e766e2d96989",
      "Action": 106,
      "Timestamp": 25.0,
      "DisplayTime": 6.0,
      "From": 1,
      "Message": "Verifique que el selector de TEMPERATURA DEL INVERSOR esté configurado en la posición 3 también (una marca de TRIÁNGULO señala esta posición de ascenso predeterminada).",
      "Value1": 0.0,
      "Value2": 0.0,
      "Value3": 0.0,
      "String1": "InvertTemp",
      "String2": "",
      "String3": "",
      "Bool1": false,
      "ThresholdLimit": 0.0,
      "PinID": 0,
      "PinPosition": 0,
      "FuseID": 0,
      "PullHandleID": 0,
      "PullHandlePosition": 0,
      "KnobID": 0,
      "ExpButtonID": 0,
      "ButtonID": 0,
      "Fault": 0,
      "Failure": 0,
      "PlayAudioClip_String3": false
    },
    {
      "Delivered": false,
      "Completed": false,
      "Priority": false,
      "Comment": "",
      "ID": "a1c2f110-f16f-4bbb-8c0f-741dd3a2229a",
      "Action": 106,
      "Timestamp": 0.0,
      "DisplayTime": 3.0,
      "From": 1,
      "Message": "Luego, asegúrate de que TRANSMIT esté configurado en UHF.",
      "Value1": 0.0,
      "Value2": 0.0,
      "Value3": 0.0,
      "String1": "PinTransmit",
      "String2": "",
      "String3": "",
      "Bool1": false,
      "ThresholdLimit": 0.0,
      "PinID": 0,
      "PinPosition": 0,
      "FuseID": 0,
      "PullHandleID": 0,
      "PullHandlePosition": 0,
      "KnobID": 0,
      "ExpButtonID": 0,
      "ButtonID": 0,
      "Fault": 0,
      "Failure": 0,
      "PlayAudioClip_String3": false
    },
    {
      "Delivered": false,
      "Completed": false,
      "Priority": false,
      "Comment": "",
      "ID": "f2dfa3bf-19c4-43be-8e7a-8584f7d8b33f",
      "Action": 1,
      "Timestamp": 25.0,
      "DisplayTime": 6.0,
      "From": 0,
      "Message": "Con el interruptor de TRANSMISIÓN configurado en UHF, realice una PRUEBA DE RADIO presionando [C] para alternar las burbujas de función y presionando el botón de PRUEBA DE RADIO. Presione ROGER una vez que haya presionado este botón.",
      "Value1": 0.0,
      "Value2": 0.0,
      "Value3": 0.0,
      "String1": "",
      "String2": "",
      "String3": "",
      "Bool1": false,
      "ThresholdLimit": 0.0,
      "PinID": 0,
      "PinPosition": 0,
      "FuseID": 0,
      "PullHandleID": 0,
      "PullHandlePosition": 0,
      "KnobID": 0,
      "ExpButtonID": 0,
      "ButtonID": 0,
      "Fault": 0,
      "Failure": 0,
      "PlayAudioClip_String3": false
    },
    {
      "Delivered": false,
      "Completed": false,
      "Priority": false,
      "Comment": "",
      "ID": "a1f22cbb-ab7a-4dcc-9666-ee58bbbf5547",
      "Action": 106,
      "Timestamp": 25.0,
      "DisplayTime": 6.0,
      "From": 0,
      "Message": "Haz clic izquierdo una vez en el botón TIEMPO CERO para quitar la cubierta, pero no presiones el botón (el botón se presionará si haces clic de nuevo después de quitar la cubierta).",
      "Value1": 0.0,
      "Value2": 0.0,
      "Value3": 0.0,
      "String1": "TimeZeroButton",
      "String2": "",
      "String3": "",
      "Bool1": false,
      "ThresholdLimit": 0.0,
      "PinID": 0,
      "PinPosition": 0,
      "FuseID": 0,
      "PullHandleID": 0,
      "PullHandlePosition": 0,
      "KnobID": 0,
      "ExpButtonID": 0,
      "ButtonID": 0,
      "Fault": 0,
      "Failure": 0,
      "PlayAudioClip_String3": false
    },
    {
      "Delivered": false,
      "Completed": false,
      "Priority": false,
      "Comment": "",
      "ID": "63a6ad8a-560f-4722-93a5-f108454f9267",
      "Action": 100,
      "Timestamp": 0.0,
      "DisplayTime": 3.0,
      "From": 1,
      "Message": "Durante el ascenso, dependiendo del Vehículo de Lanzamiento, pasarás por diferentes etapas para alcanzar la velocidad requerida para una misión. ¡El bus de SQUIB debe estar ARMADO para esto, así que ARMA los SQUIBS!",
      "Value1": 0.0,
      "Value2": 0.0,
      "Value3": 0.0,
      "String1": "",
      "String2": "",
      "String3": "",
      "Bool1": false,
      "ThresholdLimit": 0.0,
      "PinID": 15,
      "PinPosition": 1,
      "FuseID": 0,
      "PullHandleID": 0,
      "PullHandlePosition": 0,
      "KnobID": 0,
      "ExpButtonID": 0,
      "ButtonID": 0,
      "Fault": 0,
      "Failure": 0,
      "PlayAudioClip_String3": false
    },
    {
      "Delivered": false,
      "Completed": false,
      "Priority": false,
      "Comment": "",
      "ID": "df4f24a4-acf7-443b-9406-900ebce87b09",
      "Action": 100,
      "Timestamp": 0.0,
      "DisplayTime": 3.0,
      "From": 1,
      "Message": "ARMAR el [AUTO RETRO JETTISON] squib. Esto es porque se necesita armar un SQUIB especial utilizado para jettisonar nuestros motores retrógrados (más sobre esto después) en caso de un aborto. ¡No queremos armar las cosas si ocurre un aborto!",
      "Value1": 0.0,
      "Value2": 0.0,
      "Value3": 0.0,
      "String1": "",
      "String2": "",
      "String3": "",
      "Bool1": false,
      "ThresholdLimit": 0.0,
      "PinID": 18,
      "PinPosition": 1,
      "FuseID": 0,
      "PullHandleID": 0,
      "PullHandlePosition": 0,
      "KnobID": 0,
      "ExpButtonID": 0,
      "ButtonID": 0,
      "Fault": 0,
      "Failure": 0,
      "PlayAudioClip_String3": false
    },
    {
      "Delivered": false,
      "Completed": false,
      "Priority": false,
      "Comment": "",
      "ID": "c1a4c291-a5fa-4576-9c87-8dd6776eeaee",
      "Action": 0,
      "Timestamp": 25.0,
      "DisplayTime": 6.0,
      "From": 0,
      "Message": "¡Excelente, ahora estamos listos para la ascensión! Antes de continuar con la cuenta regresiva, repasemos los procedimientos de ascensión.",
      "Value1": 0.0,
      "Value2": 0.0,
      "Value3": 0.0,
      "String1": "",
      "String2": "",
      "String3": "",
      "Bool1": false,
      "ThresholdLimit": 0.0,
      "PinID": 0,
      "PinPosition": 0,
      "FuseID": 0,
      "PullHandleID": 0,
      "PullHandlePosition": 0,
      "KnobID": 0,
      "ExpButtonID": 0,
      "ButtonID": 0,
      "Fault": 0,
      "Failure": 0,
      "PlayAudioClip_String3": false
    },
    {
      "Delivered": false,
      "Completed": false,
      "Priority": false,
      "Comment": "",
      "ID": "913a48b7-c532-4ec8-a8ca-a836de313a0d",
      "Action": 1,
      "Timestamp": 25.0,
      "DisplayTime": 6.0,
      "From": 1,
      "Message": "La ascensión de Redstone dura aproximadamente 2 minutos y 30 segundos. Antes del encendido, escucharás la cuenta regresiva. Esta contará hacia el despegue.",
      "Value1": 0.0,
      "Value2": 0.0,
      "Value3": 0.0,
      "String1": "",
      "String2": "",
      "String3": "",
      "Bool1": false,
      "ThresholdLimit": 0.0,
      "PinID": 0,
      "PinPosition": 0,
      "FuseID": 0,
      "PullHandleID": 0,
      "PullHandlePosition": 0,
      "KnobID": 0,
      "ExpButtonID": 0,
      "ButtonID": 0,
      "Fault": 0,
      "Failure": 0,
      "PlayAudioClip_String3": false
    },
    {
      "Delivered": false,
      "Completed": false,
      "Priority": false,
      "Comment": "",
      "ID": "dbd38139-fa94-41ef-ae68-1a09d11349e3",
      "Action": 0,
      "Timestamp": 25.0,
      "DisplayTime": 6.0,
      "From": 0,
      "Message": "Después de esto, los motores deben ser encendidos y el cohete comenzará a ascender.",
      "Value1": 0.0,
      "Value2": 0.0,
      "Value3": 0.0,
      "String1": "",
      "String2": "",
      "String3": "",
      "Bool1": false,
      "ThresholdLimit": 0.0,
      "PinID": 0,
      "PinPosition": 0,
      "FuseID": 0,
      "PullHandleID": 0,
      "PullHandlePosition": 0,
      "KnobID": 0,
      "ExpButtonID": 0,
      "ButtonID": 0,
      "Fault": 0,
      "Failure": 0,
      "PlayAudioClip_String3": false
    },
    {
      "Delivered": false,
      "Completed": false,
      "Priority": false,
      "Comment": "",
      "ID": "ea35aea7-c868-40fc-b882-7b05d444425d",
      "Action": 0,
      "Timestamp": 25.0,
      "DisplayTime": 6.0,
      "From": 0,
      "Message": "Inmediatamente después del despegue, debemos primero monitorear que el temporizador de la misión comience. Y si no lo hace, debes presionar rápidamente el botón de TIEMPO CERO para iniciar manualmente el temporizador.",
      "Value1": 0.0,
      "Value2": 0.0,
      "Value3": 0.0,
      "String1": "",
      "String2": "",
      "String3": "",
      "Bool1": false,
      "ThresholdLimit": 0.0,
      "PinID": 0,
      "PinPosition": 0,
      "FuseID": 0,
      "PullHandleID": 0,
      "PullHandlePosition": 0,
      "KnobID": 0,
      "ExpButtonID": 0,
      "ButtonID": 0,
      "Fault": 0,
      "Failure": 0,
      "PlayAudioClip_String3": false
    },
    {
      "Delivered": false,
      "Completed": false,
      "Priority": false,
      "Comment": "",
      "ID": "2125a49d-80a0-43f1-a015-478569e93311",
      "Action": 106,
      "Timestamp": 25.0,
      "DisplayTime": 10.0,
      "From": 1,
      "Message": "El temporizador DEL TIEMPO DE LANZAMIENTO es el cronómetro de la misión, y se encuentra debajo del reloj analógico en el Reloj del Satélite.",
      "Value1": 0.0,
      "Value2": 0.0,
      "Value3": 0.0,
      "String1": "NumberDialFromLaunch",
      "String2": "",
      "String3": "",
      "Bool1": false,
      "ThresholdLimit": 0.0,
      "PinID": 0,
      "PinPosition": 0,
      "FuseID": 0,
      "PullHandleID": 0,
      "PullHandlePosition": 0,
      "KnobID": 0,
      "ExpButtonID": 0,
      "ButtonID": 0,
      "Fault": 0,
      "Failure": 0,
      "PlayAudioClip_String3": false
    },
    {
      "Delivered": false,
      "Completed": false,
      "Priority": false,
      "Comment": "",
      "ID": "65a1237e-dc54-4cd1-8bf1-1196902277d1",
      "Action": 106,
      "Timestamp": 25.0,
      "DisplayTime": 10.0,
      "From": 0,
      "Message": "Entonces debes comprobar que estás ganando altitud. Puedes usar el medidor de altitud para verificar la altitud durante el ascenso y el aterrizaje.",
      "Value1": 0.0,
      "Value2": 0.0,
      "Value3": 0.0,
      "String1": "GaugeCabinALT",
      "String2": "",
      "String3": "",
      "Bool1": false,
      "ThresholdLimit": 0.0,
      "PinID": 0,
      "PinPosition": 0,
      "FuseID": 0,
      "PullHandleID": 0,
      "PullHandlePosition": 0,
      "KnobID": 0,
      "ExpButtonID": 0,
      "ButtonID": 0,
      "Fault": 0,
      "Failure": 0,
      "PlayAudioClip_String3": false
    },
    {
      "Delivered": false,
      "Completed": false,
      "Priority": false,
      "Comment": "",
      "ID": "7fcb00ba-b255-467c-a405-9c94c1768a0d",
      "Action": 1,
      "Timestamp": 0.0,
      "DisplayTime": 3.0,
      "From": 1,
      "Message": "Una vez que estés ganando altitud, monitorea inmediatamente el reloj [TIME FROM LAUNCH] para verificar que de hecho haya empezado y siga contando.",
      "Value1": 0.0,
      "Value2": 0.0,
      "Value3": 0.0,
      "String1": "",
      "String2": "",
      "String3": "",
      "Bool1": false,
      "ThresholdLimit": 0.0,
      "PinID": 0,
      "PinPosition": 0,
      "FuseID": 0,
      "PullHandleID": 0,
      "PullHandlePosition": 0,
      "KnobID": 0,
      "ExpButtonID": 0,
      "ButtonID": 0,
      "Fault": 0,
      "Failure": 0,
      "PlayAudioClip_String3": false
    },
    {
      "Delivered": false,
      "Completed": false,
      "Priority": false,
      "Comment": "",
      "ID": "b14e5361-f339-480a-8b8a-7979dad30a9e",
      "Action": 1,
      "Timestamp": 25.0,
      "DisplayTime": 6.0,
      "From": 1,
      "Message": "La luz de ABORT en la parte superior del panel del secuenciador debe ser monitorizada continuamente (lo mejor que puedas), y si está iluminada, activa inmediatamente una ABORT al jalar la palanca de aborto. Jala la palanca presionando [CTRL]+[ALT]+[Z]. Presiona ROGER cuando hayas encontrado la luz de ABORT.",
      "Value1": 0.0,
      "Value2": 0.0,
      "Value3": 0.0,
      "String1": "",
      "String2": "",
      "String3": "",
      "Bool1": false,
      "ThresholdLimit": 0.0,
      "PinID": 0,
      "PinPosition": 0,
      "FuseID": 0,
      "PullHandleID": 0,
      "PullHandlePosition": 0,
      "KnobID": 0,
      "ExpButtonID": 0,
      "ButtonID": 0,
      "Fault": 0,
      "Failure": 0,
      "PlayAudioClip_String3": false
    },
    {
      "Delivered": false,
      "Completed": false,
      "Priority": false,
      "Comment": "",
      "ID": "fa6d7fe6-2c73-4e95-95d7-3a45fcb516ab",
      "Action": 0,
      "Timestamp": 0.0,
      "DisplayTime": 3.0,
      "From": 1,
      "Message": "Durante la ascensión, utiliza la ventana para asegurarte visualmente de que estás ascendiendo o siguiendo el horizonte. Recorre rápidamente y con frecuencia los diversos indicadores. Sé que hay muchos instrumentos, pero estos son vitales para un ascenso seguro. Permíteme abordar los más importantes.",
      "Value1": 0.0,
      "Value2": 0.0,
      "Value3": 0.0,
      "String1": "",
      "String2": "",
      "String3": "",
      "Bool1": false,
      "ThresholdLimit": 0.0,
      "PinID": 0,
      "PinPosition": 0,
      "FuseID": 0,
      "PullHandleID": 0,
      "PullHandlePosition": 0,
      "KnobID": 0,
      "ExpButtonID": 0,
      "ButtonID": 0,
      "Fault": 0,
      "Failure": 0,
      "PlayAudioClip_String3": false
    },
    {
      "Delivered": false,
      "Completed": false,
      "Priority": false,
      "Comment": "",
      "ID": "d4050d86-4b8b-44ec-bb6e-9778f356185a",
      "Action": 106,
      "Timestamp": 0.0,
      "DisplayTime": 15.0,
      "From": 1,
      "Message": "La Cápsula tiene dos Tanques de Combustible: uno para el piloto automático, y otro para el control manual. El indicador de COMBUSTIBLE DE CONTROL debe permanecer al 100% tanto para AUTO (izquierda) como para MANUAL (derecha) durante todo el ascenso.",
      "Value1": 0.0,
      "Value2": 0.0,
      "Value3": 0.0,
      "String1": "GaugeControlFuel",
      "String2": "",
      "String3": "",
      "Bool1": false,
      "ThresholdLimit": 0.0,
      "PinID": 0,
      "PinPosition": 0,
      "FuseID": 0,
      "PullHandleID": 0,
      "PullHandlePosition": 0,
      "KnobID": 0,
      "ExpButtonID": 0,
      "ButtonID": 0,
      "Fault": 0,
      "Failure": 0,
      "PlayAudioClip_String3": false
    },
    {
      "Delivered": false,
      "Completed": false,
      "Priority": false,
      "Comment": "",
      "ID": "929fab55-5967-40ba-9c46-335a51043c76",
      "Action": 106,
      "Timestamp": 0.0,
      "DisplayTime": 15.0,
      "From": 1,
      "Message": "Encima del indicador de combustible encontrarás el acelerómetro. Las fuerzas G se acumularán al acelerar. Esto normalmente subirá a 5 o 6 durante el ascenso, y hasta 12-16 durante el reingreso.",
      "Value1": 0.0,
      "Value2": 0.0,
      "Value3": 0.0,
      "String1": "GaugeAccelerometer",
      "String2": "",
      "String3": "",
      "Bool1": false,
      "ThresholdLimit": 0.0,
      "PinID": 0,
      "PinPosition": 0,
      "FuseID": 0,
      "PullHandleID": 0,
      "PullHandlePosition": 0,
      "KnobID": 0,
      "ExpButtonID": 0,
      "ButtonID": 0,
      "Fault": 0,
      "Failure": 0,
      "PlayAudioClip_String3": false
    },
    {
      "Delivered": false,
      "Completed": false,
      "Priority": false,
      "Comment": "",
      "ID": "ade8b3b1-3dc9-4b3d-9d85-77196f883662",
      "Action": 106,
      "Timestamp": 0.0,
      "DisplayTime": 15.0,
      "From": 1,
      "Message": "La cabina está ahora totalmente presurizada con oxígeno puro a presión de nivel del mar. La presión disminuirá con el tiempo. Asegúrese de que esté disminuyendo y estabilizándose en 5.5 PSIA durante el ascenso. El Sistema de Control Ambiental (ECS) mantendrá esto en 5.5. Esto se puede ver en el medidor de PRESIÓN DE LA CABINA.",
      "Value1": 0.0,
      "Value2": 0.0,
      "Value3": 0.0,
      "String1": "GaugeCabinPressure",
      "String2": "",
      "String3": "",
      "Bool1": false,
      "ThresholdLimit": 0.0,
      "PinID": 0,
      "PinPosition": 0,
      "FuseID": 0,
      "PullHandleID": 0,
      "PullHandlePosition": 0,
      "KnobID": 0,
      "ExpButtonID": 0,
      "ButtonID": 0,
      "Fault": 0,
      "Failure": 0,
      "PlayAudioClip_String3": false
    },
    {
      "Delivered": false,
      "Completed": false,
      "Priority": false,
      "Comment": "",
      "ID": "3030a17a-a45e-4a62-9ad5-10d72245ecd5",
      "Action": 106,
      "Timestamp": 0.0,
      "DisplayTime": 10.0,
      "From": 1,
      "Message": "El Programa de Inclinación automáticamente inclinará el cohete a lo largo de la trayectoria de ascenso. Asegúrate de que esto suceda revisando la aguja de inclinación en el indicador de actitud. Se moverá desde 90 hacia 0, dependiendo del perfil de la misión.",
      "Value1": 0.0,
      "Value2": 0.0,
      "Value3": 0.0,
      "String1": "Attitude 1",
      "String2": "",
      "String3": "",
      "Bool1": false,
      "ThresholdLimit": 0.0,
      "PinID": 0,
      "PinPosition": 0,
      "FuseID": 0,
      "PullHandleID": 0,
      "PullHandlePosition": 0,
      "KnobID": 0,
      "ExpButtonID": 0,
      "ButtonID": 0,
      "Fault": 0,
      "Failure": 0,
      "PlayAudioClip_String3": false
    },
    {
      "Delivered": false,
      "Completed": false,
      "Priority": false,
      "Comment": "",
      "ID": "812d4e7c-647e-45fa-a691-51ec2789774f",
      "Action": 106,
      "Timestamp": 0.0,
      "DisplayTime": 3.0,
      "From": 1,
      "Message": "La cápsula tiene dos tanques de oxígeno: uno primario y uno secundario. El ECS los está controlando automáticamente. Cuando el tanque primario esté vacío (menos del 10%), cambiará al tanque secundario.",
      "Value1": 0.0,
      "Value2": 0.0,
      "Value3": 0.0,
      "String1": "GaugeSteamOxygen",
      "String2": "",
      "String3": "",
      "Bool1": false,
      "ThresholdLimit": 0.0,
      "PinID": 0,
      "PinPosition": 0,
      "FuseID": 0,
      "PullHandleID": 0,
      "PullHandlePosition": 0,
      "KnobID": 0,
      "ExpButtonID": 0,
      "ButtonID": 0,
      "Fault": 0,
      "Failure": 0,
      "PlayAudioClip_String3": false
    },
    {
      "Delivered": false,
      "Completed": false,
      "Priority": false,
      "Comment": "",
      "ID": "85089667-90d6-48cd-ab4b-3a22e648b5b1",
      "Action": 0,
      "Timestamp": 0.0,
      "DisplayTime": 10.0,
      "From": 1,
      "Message": "Asegúrate de que los niveles de oxígeno estén al 100% durante el ascenso. Si se desprenden rápidamente o parecen extraños, haz un diagnóstico y aborta. Tienes suficiente oxígeno para respirar durante aproximadamente 24 horas. ",
      "Value1": 0.0,
      "Value2": 0.0,
      "Value3": 0.0,
      "String1": "",
      "String2": "",
      "String3": "",
      "Bool1": false,
      "ThresholdLimit": 0.0,
      "PinID": 0,
      "PinPosition": 0,
      "FuseID": 0,
      "PullHandleID": 0,
      "PullHandlePosition": 0,
      "KnobID": 0,
      "ExpButtonID": 0,
      "ButtonID": 0,
      "Fault": 0,
      "Failure": 0,
      "PlayAudioClip_String3": false
    },
    {
      "Delivered": false,
      "Completed": false,
      "Priority": false,
      "Comment": "",
      "ID": "0e06eeb6-d2d1-425e-a7e9-8866524ac38a",
      "Action": 106,
      "Timestamp": 0.0,
      "DisplayTime": 10.0,
      "From": 1,
      "Message": "Una batería en buen estado muestra 24 voltios. Como lo hicimos durante la prueba interna de energía eléctrica, selecciona qué batería monitorear usando el selector de corriente continua [DC].",
      "Value1": 0.0,
      "Value2": 0.0,
      "Value3": 0.0,
      "String1": "RotKnobDCSelection1",
      "String2": "",
      "String3": "",
      "Bool1": false,
      "ThresholdLimit": 0.0,
      "PinID": 0,
      "PinPosition": 0,
      "FuseID": 0,
      "PullHandleID": 0,
      "PullHandlePosition": 0,
      "KnobID": 0,
      "ExpButtonID": 0,
      "ButtonID": 0,
      "Fault": 0,
      "Failure": 0,
      "PlayAudioClip_String3": false
    },
    {
      "Delivered": false,
      "Completed": false,
      "Priority": false,
      "Comment": "",
      "ID": "ac942cfd-0ba3-4074-88e9-40754b1b391d",
      "Action": 106,
      "Timestamp": 25.0,
      "DisplayTime": 6.0,
      "From": 1,
      "Message": "Los voltios de CC en el sistema seleccionado se mostrarán en el medidor de VOLTIOS DE CC. También cicla a través de los voltios de todas las baterías para asegurarte de que todos estén por encima de 24.",
      "Value1": 0.0,
      "Value2": 0.0,
      "Value3": 0.0,
      "String1": "GaugeSteamDCAmps",
      "String2": "",
      "String3": "",
      "Bool1": false,
      "ThresholdLimit": 0.0,
      "PinID": 0,
      "PinPosition": 0,
      "FuseID": 0,
      "PullHandleID": 0,
      "PullHandlePosition": 0,
      "KnobID": 0,
      "ExpButtonID": 0,
      "ButtonID": 0,
      "Fault": 0,
      "Failure": 0,
      "PlayAudioClip_String3": false
    },
    {
      "Delivered": false,
      "Completed": false,
      "Priority": false,
      "Comment": "",
      "ID": "6da541ce-56e6-4ad5-862b-7500d8a5c143",
      "Action": 106,
      "Timestamp": 0.0,
      "DisplayTime": 10.0,
      "From": 1,
      "Message": "Verifica que la ALTITUD esté aumentando cuando estés por debajo de los 100.000 pies. De nuevo, es importante monitorear esto justo después del despegue para asegurarte de que estás ascendiendo.",
      "Value1": 0.0,
      "Value2": 0.0,
      "Value3": 0.0,
      "String1": "GaugeCabinALT",
      "String2": "",
      "String3": "",
      "Bool1": false,
      "ThresholdLimit": 0.0,
      "PinID": 0,
      "PinPosition": 0,
      "FuseID": 0,
      "PullHandleID": 0,
      "PullHandlePosition": 0,
      "KnobID": 0,
      "ExpButtonID": 0,
      "ButtonID": 0,
      "Fault": 0,
      "Failure": 0,
      "PlayAudioClip_String3": false
    },
    {
      "Delivered": false,
      "Completed": false,
      "Priority": false,
      "Comment": "",
      "ID": "fbc53f2a-1b87-4702-a5db-3ba6a17a98bd",
      "Action": 106,
      "Timestamp": 0.0,
      "DisplayTime": 10.0,
      "From": 1,
      "Message": "Verifique la temperatura del aire de la cabina, se mide en grados Fahrenheit. Si está demasiado frío o demasiado cálido, ajuste la configuración de temperatura debajo de la escotilla (panel más a la derecha). Nunca exceda los 120 grados Fahrenheit en ninguno de los circuitos.",
      "Value1": 0.0,
      "Value2": 0.0,
      "Value3": 0.0,
      "String1": "GaugeCabinAir",
      "String2": "",
      "String3": "",
      "Bool1": false,
      "ThresholdLimit": 0.0,
      "PinID": 0,
      "PinPosition": 0,
      "FuseID": 0,
      "PullHandleID": 0,
      "PullHandlePosition": 0,
      "KnobID": 0,
      "ExpButtonID": 0,
      "ButtonID": 0,
      "Fault": 0,
      "Failure": 0,
      "PlayAudioClip_String3": false
    },
    {
      "Delivered": false,
      "Completed": false,
      "Priority": false,
      "Comment": "",
      "ID": "fb7fa1f5-ec93-47bf-b310-498c41902373",
      "Action": 0,
      "Timestamp": 0.0,
      "DisplayTime": 10.0,
      "From": 1,
      "Message": "Los indicadores del Secuenciador a la izquierda del panel principal se iluminarán según la etapa en la que te encuentres. El color blanco significa que no está procesando, el color naranja significa que está procesando (o que algo necesita atención) y el color verde significa que el paso está completo.",
      "Value1": 0.0,
      "Value2": 0.0,
      "Value3": 0.0,
      "String1": "",
      "String2": "",
      "String3": "",
      "Bool1": false,
      "ThresholdLimit": 0.0,
      "PinID": 0,
      "PinPosition": 0,
      "FuseID": 0,
      "PullHandleID": 0,
      "PullHandlePosition": 0,
      "KnobID": 0,
      "ExpButtonID": 0,
      "ButtonID": 0,
      "Fault": 0,
      "Failure": 0,
      "PlayAudioClip_String3": false
    },
    {
      "Delivered": false,
      "Completed": false,
      "Priority": false,
      "Comment": "",
      "ID": "41798e0d-b5c1-4aeb-9d79-7682dba7c87b",
      "Action": 0,
      "Timestamp": 25.0,
      "DisplayTime": 6.0,
      "From": 1,
      "Message": "Si has hecho todo correctamente, el cohete debería estar listo para la ignición.",
      "Value1": 0.0,
      "Value2": 0.0,
      "Value3": 0.0,
      "String1": "",
      "String2": "",
      "String3": "",
      "Bool1": false,
      "ThresholdLimit": 0.0,
      "PinID": 0,
      "PinPosition": 0,
      "FuseID": 0,
      "PullHandleID": 0,
      "PullHandlePosition": 0,
      "KnobID": 0,
      "ExpButtonID": 0,
      "ButtonID": 0,
      "Fault": 0,
      "Failure": 0,
      "PlayAudioClip_String3": false
    },
    {
      "Delivered": false,
      "Completed": false,
      "Priority": false,
      "Comment": "",
      "ID": "bf014f22-4664-44ed-8d40-32101e09fc3a",
      "Action": 1,
      "Timestamp": 25.0,
      "DisplayTime": 6.0,
      "From": 1,
      "Message": "Para resumir todo. Al despegar, verifica que el reloj esté en marcha y que estés aumentando en altitud. Luego monitorea la luz de aborto mientras pasas por las fuerzas G, los niveles de combustible, la presión de la cabina, la cantidad total de oxígeno, los voltios de CC del bus principal.",
      "Value1": 0.0,
      "Value2": 0.0,
      "Value3": 0.0,
      "String1": "",
      "String2": "",
      "String3": "",
      "Bool1": false,
      "ThresholdLimit": 0.0,
      "PinID": 0,
      "PinPosition": 0,
      "FuseID": 0,
      "PullHandleID": 0,
      "PullHandlePosition": 0,
      "KnobID": 0,
      "ExpButtonID": 0,
      "ButtonID": 0,
      "Fault": 0,
      "Failure": 0,
      "PlayAudioClip_String3": false
    },
    {
      "Delivered": false,
      "Completed": false,
      "Priority": false,
      "Comment": "",
      "ID": "e8e68f08-ccf5-484e-bfda-368985bce733",
      "Action": 507,
      "Timestamp": 25.0,
      "DisplayTime": 6.0,
      "From": 0,
      "Message": "He retomado ahora la cuenta regresiva. Si necesitas más tiempo, siéntete libre de pausar y reanudar manualmente. Utiliza la escala de tiempo hasta el despegue.",
      "Value1": 0.0,
      "Value2": 0.0,
      "Value3": 0.0,
      "String1": "",
      "String2": "",
      "String3": "",
      "Bool1": false,
      "ThresholdLimit": 0.0,
      "PinID": 0,
      "PinPosition": 0,
      "FuseID": 0,
      "PullHandleID": 0,
      "PullHandlePosition": 0,
      "KnobID": 0,
      "ExpButtonID": 0,
      "ButtonID": 0,
      "Fault": 0,
      "Failure": 0,
      "PlayAudioClip_String3": false
    },
    {
      "Delivered": false,
      "Completed": false,
      "Priority": false,
      "Comment": "",
      "ID": "43fe699a-cd87-4c07-b209-efe7599f8aa1",
      "Action": 79,
      "Timestamp": 1170.0,
      "DisplayTime": 6.0,
      "From": 1,
      "Message": "30 segundos para el encendido. ¡Buena suerte, {profileName}!",
      "Value1": 0.0,
      "Value2": 0.0,
      "Value3": 0.0,
      "String1": "",
      "String2": "",
      "String3": "",
      "Bool1": false,
      "ThresholdLimit": 0.0,
      "PinID": 0,
      "PinPosition": 0,
      "FuseID": 0,
      "PullHandleID": 0,
      "PullHandlePosition": 0,
      "KnobID": 0,
      "ExpButtonID": 0,
      "ButtonID": 0,
      "Fault": 0,
      "Failure": 0,
      "PlayAudioClip_String3": false
    },
    {
      "Delivered": false,
      "Completed": false,
      "Priority": false,
      "Comment": "",
      "ID": "70c44015-bdde-4b77-bef9-18a2a44ffaad",
      "Action": 106,
      "Timestamp": 1.0,
      "DisplayTime": 3.0,
      "From": 1,
      "Message": "¡Despegue! Verifique inmediatamente si el cronómetro está contando.",
      "Value1": 0.0,
      "Value2": 0.0,
      "Value3": 0.0,
      "String1": "NumberDialFromLaunch",
      "String2": "",
      "String3": "",
      "Bool1": false,
      "ThresholdLimit": 0.0,
      "PinID": 0,
      "PinPosition": 0,
      "FuseID": 0,
      "PullHandleID": 0,
      "PullHandlePosition": 0,
      "KnobID": 0,
      "ExpButtonID": 0,
      "ButtonID": 0,
      "Fault": 0,
      "Failure": 0,
      "PlayAudioClip_String3": false
    },
    {
      "Delivered": false,
      "Completed": false,
      "Priority": false,
      "Comment": "",
      "ID": "df39a40e-7264-46b5-b3d2-b6b4c94962d2",
      "Action": 106,
      "Timestamp": 1.0,
      "DisplayTime": 6.0,
      "From": 0,
      "Message": "Luego verifica que el cohete está ganando altitud.",
      "Value1": 0.0,
      "Value2": 0.0,
      "Value3": 0.0,
      "String1": "GaugeCabinALT",
      "String2": "",
      "String3": "",
      "Bool1": false,
      "ThresholdLimit": 0.0,
      "PinID": 0,
      "PinPosition": 0,
      "FuseID": 0,
      "PullHandleID": 0,
      "PullHandlePosition": 0,
      "KnobID": 0,
      "ExpButtonID": 0,
      "ButtonID": 0,
      "Fault": 0,
      "Failure": 0,
      "PlayAudioClip_String3": false
    },
    {
      "Delivered": false,
      "Completed": false,
      "Priority": false,
      "Comment": "",
      "ID": "8959ff7e-8974-47a9-8fd1-b923b8f1fe63",
      "Action": 1,
      "Timestamp": 0.0,
      "DisplayTime": 3.0,
      "From": 1,
      "Message": "Utiliza la ventana para asegurarte visualmente de que estás subiendo o inclinándote lentamente hacia el horizonte. Durante el resto del ascenso, monitorea los instrumentos clave. Vamos a dar una vuelta rápida juntos.",
      "Value1": 0.0,
      "Value2": 0.0,
      "Value3": 0.0,
      "String1": "",
      "String2": "",
      "String3": "",
      "Bool1": false,
      "ThresholdLimit": 0.0,
      "PinID": 0,
      "PinPosition": 0,
      "FuseID": 0,
      "PullHandleID": 0,
      "PullHandlePosition": 0,
      "KnobID": 0,
      "ExpButtonID": 0,
      "ButtonID": 0,
      "Fault": 0,
      "Failure": 0,
      "PlayAudioClip_String3": false
    },
    {
      "Delivered": false,
      "Completed": false,
      "Priority": false,
      "Comment": "",
      "ID": "d62c0dfc-6360-4926-8352-919fdc08b886",
      "Action": 106,
      "Timestamp": 0.0,
      "DisplayTime": 15.0,
      "From": 1,
      "Message": "Verifique que ambos tanques de combustible, AUTO y MANUAL, estén al ~100%.",
      "Value1": 0.0,
      "Value2": 0.0,
      "Value3": 0.0,
      "String1": "GaugeControlFuel",
      "String2": "",
      "String3": "",
      "Bool1": false,
      "ThresholdLimit": 0.0,
      "PinID": 0,
      "PinPosition": 0,
      "FuseID": 0,
      "PullHandleID": 0,
      "PullHandlePosition": 0,
      "KnobID": 0,
      "ExpButtonID": 0,
      "ButtonID": 0,
      "Fault": 0,
      "Failure": 0,
      "PlayAudioClip_String3": false
    },
    {
      "Delivered": false,
      "Completed": false,
      "Priority": false,
      "Comment": "",
      "ID": "0539bc9e-0140-45fa-80a6-5e42705a141c",
      "Action": 106,
      "Timestamp": 0.0,
      "DisplayTime": 15.0,
      "From": 1,
      "Message": "Verifica las Fuerzas G, deberían llegar hasta 6 g's.",
      "Value1": 0.0,
      "Value2": 0.0,
      "Value3": 0.0,
      "String1": "GaugeAccelerometer",
      "String2": "",
      "String3": "",
      "Bool1": false,
      "ThresholdLimit": 0.0,
      "PinID": 0,
      "PinPosition": 0,
      "FuseID": 0,
      "PullHandleID": 0,
      "PullHandlePosition": 0,
      "KnobID": 0,
      "ExpButtonID": 0,
      "ButtonID": 0,
      "Fault": 0,
      "Failure": 0,
      "PlayAudioClip_String3": false
    },
    {
      "Delivered": false,
      "Completed": false,
      "Priority": false,
      "Comment": "",
      "ID": "76b675de-7258-4fbe-93b4-055cf42ad75c",
      "Action": 106,
      "Timestamp": 0.0,
      "DisplayTime": 15.0,
      "From": 1,
      "Message": "Verifique que la presión de la cabina esté descendiendo y eventualmente se detenga en 5.5 psia.",
      "Value1": 0.0,
      "Value2": 0.0,
      "Value3": 0.0,
      "String1": "GaugeCabinPressure",
      "String2": "",
      "String3": "",
      "Bool1": false,
      "ThresholdLimit": 0.0,
      "PinID": 0,
      "PinPosition": 0,
      "FuseID": 0,
      "PullHandleID": 0,
      "PullHandlePosition": 0,
      "KnobID": 0,
      "ExpButtonID": 0,
      "ButtonID": 0,
      "Fault": 0,
      "Failure": 0,
      "PlayAudioClip_String3": false
    },
    {
      "Delivered": false,
      "Completed": false,
      "Priority": false,
      "Comment": "",
      "ID": "b958241e-a60a-4277-8b9b-834850616ec6",
      "Action": 106,
      "Timestamp": 0.0,
      "DisplayTime": 10.0,
      "From": 1,
      "Message": "Monitorea el programa del paso, el cohete debería alinearse lentamente hacia el horizonte.",
      "Value1": 0.0,
      "Value2": 0.0,
      "Value3": 0.0,
      "String1": "Attitude 1",
      "String2": "",
      "String3": "",
      "Bool1": false,
      "ThresholdLimit": 0.0,
      "PinID": 0,
      "PinPosition": 0,
      "FuseID": 0,
      "PullHandleID": 0,
      "PullHandlePosition": 0,
      "KnobID": 0,
      "ExpButtonID": 0,
      "ButtonID": 0,
      "Fault": 0,
      "Failure": 0,
      "PlayAudioClip_String3": false
    },
    {
      "Delivered": false,
      "Completed": false,
      "Priority": false,
      "Comment": "",
      "ID": "0037017e-44b1-48bb-acea-cdfe2e007038",
      "Action": 106,
      "Timestamp": 0.0,
      "DisplayTime": 3.0,
      "From": 1,
      "Message": "Verifique la cantidad total de oxígeno ([O2]).",
      "Value1": 0.0,
      "Value2": 0.0,
      "Value3": 0.0,
      "String1": "GaugeSteamOxygen",
      "String2": "",
      "String3": "",
      "Bool1": false,
      "ThresholdLimit": 0.0,
      "PinID": 0,
      "PinPosition": 0,
      "FuseID": 0,
      "PullHandleID": 0,
      "PullHandlePosition": 0,
      "KnobID": 0,
      "ExpButtonID": 0,
      "ButtonID": 0,
      "Fault": 0,
      "Failure": 0,
      "PlayAudioClip_String3": false
    },
    {
      "Delivered": false,
      "Completed": false,
      "Priority": false,
      "Comment": "",
      "ID": "e5b572d0-c0c7-432b-b3e4-5c27e9bf5c49",
      "Action": 106,
      "Timestamp": 0.0,
      "DisplayTime": 10.0,
      "From": 1,
      "Message": "Revisa el BUS PRINCIPAL DE CC y gira totalmente el SELECTOR DE CC cada 1 minuto y 30 segundos mientras revisas todas las baterías, luego devuélvelo a PRINCIPAL.",
      "Value1": 0.0,
      "Value2": 0.0,
      "Value3": 0.0,
      "String1": "RotKnobDCSelection1",
      "String2": "",
      "String3": "",
      "Bool1": false,
      "ThresholdLimit": 0.0,
      "PinID": 0,
      "PinPosition": 0,
      "FuseID": 0,
      "PullHandleID": 0,
      "PullHandlePosition": 0,
      "KnobID": 0,
      "ExpButtonID": 0,
      "ButtonID": 0,
      "Fault": 0,
      "Failure": 0,
      "PlayAudioClip_String3": false
    },
    {
      "Delivered": false,
      "Completed": false,
      "Priority": false,
      "Comment": "",
      "ID": "ee73fc42-2a0b-492f-b593-4a650635e9d9",
      "Action": 106,
      "Timestamp": 0.0,
      "DisplayTime": 10.0,
      "From": 1,
      "Message": "Verifica la altitud.",
      "Value1": 0.0,
      "Value2": 0.0,
      "Value3": 0.0,
      "String1": "GaugeCabinALT",
      "String2": "",
      "String3": "",
      "Bool1": false,
      "ThresholdLimit": 0.0,
      "PinID": 0,
      "PinPosition": 0,
      "FuseID": 0,
      "PullHandleID": 0,
      "PullHandlePosition": 0,
      "KnobID": 0,
      "ExpButtonID": 0,
      "ButtonID": 0,
      "Fault": 0,
      "Failure": 0,
      "PlayAudioClip_String3": false
    },
    {
      "Delivered": false,
      "Completed": false,
      "Priority": false,
      "Comment": "",
      "ID": "037e442b-10c1-4ed2-9829-8292cc8fa9ff",
      "Action": 106,
      "Timestamp": 0.0,
      "DisplayTime": 10.0,
      "From": 1,
      "Message": "Verifique la temperatura del aire de la cabina, asegúrese de que esté por debajo de 120 grados Fahrenheit.",
      "Value1": 0.0,
      "Value2": 0.0,
      "Value3": 0.0,
      "String1": "GaugeCabinAir",
      "String2": "",
      "String3": "",
      "Bool1": false,
      "ThresholdLimit": 0.0,
      "PinID": 0,
      "PinPosition": 0,
      "FuseID": 0,
      "PullHandleID": 0,
      "PullHandlePosition": 0,
      "KnobID": 0,
      "ExpButtonID": 0,
      "ButtonID": 0,
      "Fault": 0,
      "Failure": 0,
      "PlayAudioClip_String3": false
    },
    {
      "Delivered": false,
      "Completed": false,
      "Priority": false,
      "Comment": "",
      "ID": "d8c65a3c-9674-4f1c-824b-e1b5e0ceba39",
      "Action": 0,
      "Timestamp": 0.0,
      "DisplayTime": 10.0,
      "From": 1,
      "Message": "Monitorea las luces del secuenciador para que las de JETT TOWER y SEP CAPSULE se pongan verdes.",
      "Value1": 0.0,
      "Value2": 0.0,
      "Value3": 0.0,
      "String1": "",
      "String2": "",
      "String3": "",
      "Bool1": false,
      "ThresholdLimit": 0.0,
      "PinID": 0,
      "PinPosition": 0,
      "FuseID": 0,
      "PullHandleID": 0,
      "PullHandlePosition": 0,
      "KnobID": 0,
      "ExpButtonID": 0,
      "ButtonID": 0,
      "Fault": 0,
      "Failure": 0,
      "PlayAudioClip_String3": false
    },
    {
      "Delivered": false,
      "Completed": false,
      "Priority": false,
      "Comment": "",
      "ID": "30488cd3-7d42-4e60-888c-bcd66d5f3420",
      "Action": 0,
      "Timestamp": 0.0,
      "DisplayTime": 6.0,
      "From": 1,
      "Message": "Repite este ciclo durante la ascensión.",
      "Value1": 0.0,
      "Value2": 0.0,
      "Value3": 0.0,
      "String1": "",
      "String2": "",
      "String3": "",
      "Bool1": false,
      "ThresholdLimit": 0.0,
      "PinID": 0,
      "PinPosition": 0,
      "FuseID": 0,
      "PullHandleID": 0,
      "PullHandlePosition": 0,
      "KnobID": 0,
      "ExpButtonID": 0,
      "ButtonID": 0,
      "Fault": 0,
      "Failure": 0,
      "PlayAudioClip_String3": false
    },
    {
      "Delivered": false,
      "Completed": false,
      "Priority": false,
      "Comment": "",
      "ID": "42341f0f-9c34-4aee-89c9-1a4e89e25ebc",
      "Action": 0,
      "Timestamp": 25.0,
      "DisplayTime": 6.0,
      "From": 1,
      "Message": "Una vez que la torre es eyectada, y la cápsula se separa, el ascenso está completo. Después del ascenso, la cápsula girará 180 grados y te ubicará automáticamente en una actitud orbital normal.",
      "Value1": 0.0,
      "Value2": 0.0,
      "Value3": 0.0,
      "String1": "",
      "String2": "",
      "String3": "",
      "Bool1": false,
      "ThresholdLimit": 0.0,
      "PinID": 0,
      "PinPosition": 0,
      "FuseID": 0,
      "PullHandleID": 0,
      "PullHandlePosition": 0,
      "KnobID": 0,
      "ExpButtonID": 0,
      "ButtonID": 0,
      "Fault": 0,
      "Failure": 0,
      "PlayAudioClip_String3": false
    },
    {
      "Delivered": false,
      "Completed": false,
      "Priority": false,
      "Comment": "",
      "ID": "44501e8b-e8c8-4a00-a60a-0585ffd5840b",
      "Action": 501,
      "Timestamp": 120.0,
      "DisplayTime": 6.0,
      "From": 1,
      "Message": "",
      "Value1": 0.0,
      "Value2": 0.0,
      "Value3": 0.0,
      "String1": "",
      "String2": "",
      "String3": "",
      "Bool1": false,
      "ThresholdLimit": 0.0,
      "PinID": 0,
      "PinPosition": 0,
      "FuseID": 0,
      "PullHandleID": 0,
      "PullHandlePosition": 0,
      "KnobID": 0,
      "ExpButtonID": 0,
      "ButtonID": 0,
      "Fault": 0,
      "Failure": 2,
      "PlayAudioClip_String3": false
    },
    {
      "Delivered": false,
      "Completed": false,
      "Priority": false,
      "Comment": "",
      "ID": "8e996d6a-3b84-4072-b2ca-e3439687ef8c",
      "Action": 72,
      "Timestamp": 0.0,
      "DisplayTime": 3.0,
      "From": 1,
      "Message": "",
      "Value1": 0.0,
      "Value2": 0.0,
      "Value3": 0.0,
      "String1": "",
      "String2": "",
      "String3": "",
      "Bool1": false,
      "ThresholdLimit": 0.0,
      "PinID": 0,
      "PinPosition": 0,
      "FuseID": 0,
      "PullHandleID": 0,
      "PullHandlePosition": 0,
      "KnobID": 0,
      "ExpButtonID": 0,
      "ButtonID": 0,
      "Fault": 0,
      "Failure": 0,
      "PlayAudioClip_String3": false
    },
    {
      "Delivered": false,
      "Completed": false,
      "Priority": false,
      "Comment": "",
      "ID": "686d4154-9b60-4bca-9a0e-1c92c97a26ff",
      "Action": 0,
      "Timestamp": 25.0,
      "DisplayTime": 6.0,
      "From": 1,
      "Message": "¡Excelente, gran trabajo hoy! Recomiendo ensayar ascensos utilizando la misión Redstone Free Flight. Y puntos extra para ti si lograste detectar que la tercera batería falló durante el ascenso.",
      "Value1": 0.0,
      "Value2": 0.0,
      "Value3": 0.0,
      "String1": "",
      "String2": "",
      "String3": "",
      "Bool1": false,
      "ThresholdLimit": 0.0,
      "PinID": 0,
      "PinPosition": 0,
      "FuseID": 0,
      "PullHandleID": 0,
      "PullHandlePosition": 0,
      "KnobID": 0,
      "ExpButtonID": 0,
      "ButtonID": 0,
      "Fault": 0,
      "Failure": 0,
      "PlayAudioClip_String3": false
    },
    {
      "Delivered": false,
      "Completed": false,
      "Priority": false,
      "Comment": "",
      "ID": "23ae1df1-8770-48e5-9c1b-815592acfa48",
      "Action": 1006,
      "Timestamp": 0.0,
      "DisplayTime": 3.0,
      "From": 1,
      "Message": "¡Excelente, buen trabajo, esto concluye la lección de ascenso!",
      "Value1": 0.0,
      "Value2": 0.0,
      "Value3": 0.0,
      "String1": "",
      "String2": "",
      "String3": "",
      "Bool1": false,
      "ThresholdLimit": 0.0,
      "PinID": 0,
      "PinPosition": 0,
      "FuseID": 0,
      "PullHandleID": 0,
      "PullHandlePosition": 0,
      "KnobID": 0,
      "ExpButtonID": 0,
      "ButtonID": 0,
      "Fault": 0,
      "Failure": 0,
      "PlayAudioClip_String3": false
    }
  ],
  "MissionGoals": [
    {
      "Progress": null,
      "Completed": false,
      "Type": 2,
      "Description": "Complete the lesson",
      "Target1": 0.0,
      "Target2": 0.0,
      "Target3": 0.0,
      "String1": "",
      "String2": ""
    }
  ],
  "MissionActivities": [],
  "MissionChecklists": [],
  "MissionInsigniaPath": "",
  "SpaceProgram": 0,
  "Id": 101,
  "ID": "3707ea67-d2ce-4f7c-8b38-bf108582cbf7",
  "Title": "Tutorial 2 - Lanzamiento y ascenso",
  "Description": "En esta lección repasaremos todos los pasos necesarios para el lanzamiento y el ascenso. Afortunadamente, el ascenso es un proceso automatizado, pero pueden ocurrir emergencias, por lo que tu tarea será monitorear los medidores periódicamente mientras te preparas para un aborto de misión.",
  "BriefingText": "BRIEFING\r\n\r\nEn esta lección repasaremos todos los pasos necesarios para el lanzamiento y el ascenso. Afortunadamente, el ascenso es un proceso automatizado, pero pueden ocurrir emergencias. Tu tarea será monitorear todos los medidores periódicamente mientras te preparas para un aborto de misión.",
  "FlightPlanPrefabId": 0,
  "MinutesBeforeLaunch": 20.0,
  "TargetAp": 100.0,
  "TargetPe": 100.0,
  "Inclination": 33.0,
  "DisableDefaultAudioSFX": false,
  "LoadState": "",
  "OverridePanelState": false,
  "OverridePanelStateFileName": "Default/Ingress.json",
  "AllowRandomFailures": false,
  "OverrideSunPhase": false,
  "OverrideSunPhaseValue": 0.0,
  "RealisticRadioRange": false,
  "LongDurationMissionSetup": false
}